Workbook

Sheet Leia primeiro
A1: Planilhas do Vem Trabalhar
A2: Versão 4, de 06/10/2026: entrevista do currículo, IA para o dono, comandos de voz e benchmark. Tudo que é pergunta é de tocar. Células amarelas com letra azul são suas.
A4: Em uma frase
A5: Um método só, do trabalhador autônomo até a empresa de mil funcionários: a mesma pessoa se cadastra, aprende, é avaliada com transparência e é encontrada pela vaga certa.
A7: Como os cursos funcionam
A8: Cursos nossos: só cursos livres, feitos por nós, com certificado de curso livre. Não usamos cursos de terceiros (Sebrae, Fundação Bradesco, Sistema S): ficaram de fora.
A9: Cursos técnicos e faculdades: entram por parceria. A escola paga ao Vem Trabalhar 50% da matrícula e 30% de cada mensalidade (como entendi sua fala; confirmar com cada escola).
A10: A comissão nunca muda a nota do match. O curso de parceiro aparece com a etiqueta 'Parceiro', para a pessoa saber que existe um acordo.
A12: O que tem em cada aba (toque no nome para ir)
A13: Parcerias | B13: Regra de comissão (50% da matrícula, 30% da mensalidade), calculadora e regras do acordo com escolas.
A14: Portal do parceiro | B14: O passo a passo da escola: cadastra a si, os cursos e as empresas; aparece ao aluno com a etiqueta Parceiro; comissão nasce da matrícula e das mensalidades.
A15: Escolas técnicas | B15: Lista de escolas técnicas parceiras, para você preencher: curso, matrícula, mensalidade, comissão por aluno, situação.
A16: Faculdades | B16: A mesma lista, para faculdades e universidades.
A17: Cursos com parceiros | B17: 31 cursos que queremos com escola parceira (técnicos e mistos), com quem emite o documento.
A18: Ideias de cursos | B18: 71 cursos livres nossos, com a atividade de toque de cada um. A meta de 200 se acompanha no topo.
A19: Cursos próprios | B19: Como é um curso nosso: lições curtas, atividade de toque, reteste, prova final, certificado.
A20: Canais | B20: 14 formas de entrar e de manter contato todo dia com as pessoas, com o que já pode rodar em 13/10.
A21: Sistema vivo | B21: Os agentes que propõem melhoria (benchmark, cursos, vídeos, match) e quem aprova.
A22: IA para o dono | B22: Os 3 pilares do texto da V4 (conteúdo em escala, análise de dados, imagens) e como cada um vira função, por voz ou foto, para cada dono que comprar o software.
A23: Comandos de voz | B23: 32 frases de exemplo: o dono, o gerente, o candidato e você falam, e o sistema faz, pedindo confirmação quando mexe com dinheiro.
A24: Benchmark | B24: O que vimos de novo no mercado e onde entra. O agente de benchmark acrescenta linhas; a coluna amarela é a sua decisão.
... A36: Fontes | B36: De onde vieram os testes.
A38: Mesmo método, qualquer tamanho de empresa
A39: Quem é | B39: O que vê na tela (proposta nossa) | C39: Plano por vagas por mês (decisão do GD, 06/10/2026)
A40: Quem trabalha sozinho (MEI, autônomo) | B40: Uma vaga de 1 toque, perfil pronto, cursos de gestão do pequeno negócio. | C40: 0 a 10 vagas: R$ 300
A41: Empresa com 2 a 50 funcionários | B41: As mesmas telas, com a vaga montada em 20 respostas de toque e a lista de candidatos já ordenada. | C41: 0 a 10 vagas: R$ 300; 11 a 500: R$ 500
A42: Empresa com 51 a 500 funcionários | B42: Acrescenta a avaliação de desempenho dos funcionários e os relatórios por setor. | C42: 11 a 500 vagas: R$ 500
A43: Empresa com 501 a 1.000 funcionários | B43: Acrescenta vários gestores, vários locais e relatórios por região. | C43: 501 a 1.000 vagas: R$ 1.000
A44: Mais de 1.000 | B44: Mesmo método, com contrato sob medida. | C44: Acima de 1.000 vagas: negociado
A45: Observação: o GD disse '11 a 50 = R$ 500' e '51 a 500 = R$ 500'; tratei como uma faixa só, de 11 a 500. O candidato paga R$ 80 (mensal ou uma vez: pergunta aberta). Semana de teste grátis, sem baixar nada.
A47: Regras que valem em tudo
A48: Ninguém é eliminado por nota ou por prova. A prova final de um curso só dá o certificado; quem não passa refaz com perguntas novas.
A49: A pessoa vê o que a empresa vê sobre ela e vê por que a nota deu aquele valor, com o curso que a faria subir.
A50: Dados sensíveis não entram no match: raça ou cor, religião, estado civil, filhos, gravidez, idade como filtro, saúde, orientação sexual, opinião política.
A51: Aviso de vaga, de curso e uso das respostas para estudo ou marketing só com consentimento separado, desmarcado de início e revogável.
A52: Funcionário sabe que está sendo avaliado e vê o próprio resultado. Avaliação serve para desenvolver, não para demitir de forma automática.
A53: Teste de jeito de ser e de interesses é para a pessoa se conhecer. Só vai para a empresa se ela autorizar, e nunca elimina.
A54: Certificado do Vem Trabalhar é de curso livre. Diploma técnico ou superior só instituição credenciada emite.
A55: Curso de parceiro leva a etiqueta 'Parceiro'. A comissão não entra na conta do match.
A56: O banco de pessoas só cresce com consentimento: nada de lista comprada, nada de raspar Instagram, nada de mensagem fora do aceite.
A57: Antes de abrir o cadastro e de fechar a primeira parceria: revisão de advogado (LGPD, Lei 9.029/1995, testes na seleção, avaliação de funcionários, contrato com as escolas).
... A80: 10. Currículo na semana de teste: só ver na tela, e baixar o PDF libera com o pagamento. Combinado? (Se o básico for grátis, como na pergunta 4, o PDF simples sai de graça.)

Sheet Parcerias
A1: Parcerias com escolas: como o Vem Trabalhar ganha
A2: A escola paga ao Vem Trabalhar uma comissão sobre cada aluno que trouxermos. Letra azul em fundo amarelo = você pode mudar.
A4: Regra | B4: Valor | C4: Observação
A5: Comissão sobre a matrícula | B5: 0.5 | C5: Como entendi sua fala: 50% da matrícula.
A6: Comissão sobre cada mensalidade | B6: 0.3 | C6: Como entendi sua fala: 30% da mensalidade.
A7: Quantas mensalidades pagam comissão | B7: 12 | C7: Premissa nossa (12). Pergunta aberta: vale por todas as mensalidades ou por um período?
A8: Quem paga | B8: A escola | C8: O aluno paga o preço normal da escola. A comissão sai da escola, não de um acréscimo ao aluno.
A10: Exemplo de conta (valores inventados) | B10: Valor | C10: Como calcula
A11: Matrícula (R$) | B11: 200 | C11: Exemplo
A12: Mensalidade (R$) | B12: 400 | C12: Exemplo
A13: Alunos que trouxemos | B13: 10 | C13: Exemplo
A14: Comissão por aluno (R$) | B14: =B11*B5+B12*B6*B7 -> 1540 | C14: matrícula x comissão da matrícula + mensalidade x comissão da mensalidade x número de mensalidades
A15: Receita do Vem Trabalhar com esses alunos (R$) | B15: =B14*B13 -> 15400 | C15: comissão por aluno x alunos
A17: Regras do acordo com escola
A18: Contrato por escola, revisado por advogado, dizendo quem paga, quando e como o Vem Trabalhar comprova que o aluno veio por nós.
A19: A escola precisa ser credenciada. Para faculdade, conferir no cadastro oficial do MEC (e-MEC); para escola técnica, no sistema de ensino do estado. Endereços e regras a confirmar.
A20: Curso de parceiro leva a etiqueta 'Parceiro'. A comissão nunca muda a nota do match nem a ordem das vagas.
A21: O diploma é da escola. O Vem Trabalhar nunca chama o próprio certificado de diploma.
A22: Meta de acompanhamento: quantos alunos por escola, quantos concluíram, quantos conseguiram vaga.

Sheet Portal do parceiro
A1: Portal do parceiro: a escola se cadastra e cadastra os próprios cursos e empresas
A2: Cada escola entra por um link, preenche tudo de toque e aparece para os alunos junto com os cursos livres, com a etiqueta 'Parceiro'.
A4: Etapa | B4: O que a escola faz | C4: O que o aluno vê | D4: Dado guardado | E4: Regra
A5: 1. Quero ser parceiro | B5: Entra por um link ou QR, informa nome, CNPJ, cidade, responsável e aceita o contrato. | C5: Nada ainda. | D5: Dados da instituição e aceite do contrato (data e versão). | E5: O aceite é do contrato revisado por advogado. Sem aceite, não publica nada.
A6: 2. Conferência | B6: Espera a conferência. | C6: Nada ainda. | D6: Situação: pendente, conferida ou recusada. | E6: Nós conferimos o credenciamento (faculdade: cadastro oficial do MEC; escola técnica: sistema de ensino do estado). Endereços e regras a confirmar.
A7: 3. Cadastrar curso | B7: Informa curso, tipo (técnico, graduação, curso livre pago), modalidade, CEP do local, duração, matrícula, mensalidade, vagas por turma, início e link de inscrição. | C7: Ficha do curso com preço, local, tempo de deslocamento e se é EAD ou presencial. | D7: Curso, preço, vagas, local (CEP) e data de início. | E7: Preço publicado é o preço normal da escola. O aluno não paga a mais por vir pelo Vem Trabalhar.
A8: 4. Cadastrar empresas | B8: Informa as empresas que contratam seus alunos (convênios de estágio e emprego) e as vagas que elas têm. | C8: As vagas aparecem no match, como as de qualquer empresa. | D8: Empresa e vaga ligadas à escola. | E8: A empresa precisa aceitar. As vagas seguem o mesmo método de 20 perguntas.
A9: 5. Publicar | B9: Toca em publicar. | C9: O curso aparece na tela de cursos, depois dos cursos livres que cobrem a mesma habilidade, com a etiqueta 'Parceiro'. | D9: Curso publicado, data e versão. | E9: A comissão nunca muda a nota do match nem a ordem.
A10: 6. Interesse do aluno | B10: Recebe o aviso de que alguém tem interesse (WhatsApp ou e-mail). | C10: Toca em 'Tenho interesse' e autoriza a escola a falar com ele. | D10: Interesse, consentimento do aluno, data e código de origem. | E10: Só vai para a escola quem tocou e autorizou. Nada de lista vendida.
A11: 7. Matrícula | B11: Marca 'matriculou' e anexa o comprovante. | C11: Confirma 'me matriculei' no app. | D11: Matrícula confirmada pelas duas pontas. | E11: A comissão da matrícula só nasce quando escola e aluno confirmam. Se houver divergência, a conta fica em análise.
A12: 8. Mensalidades | B12: Todo mês marca quem pagou ou envia a lista. | C12: Vê o curso na sua trilha. | D12: Mensalidade paga, por aluno e mês. | E12: A comissão da mensalidade nasce a cada mês pago. A escola aceita auditoria no contrato.
A13: 9. Extrato | B13: Vê o que deve, o que pagou e paga por Pix. | C13: - | D13: Comissões a receber e pagas, por escola, aluno e mês. | E13: Vencimento e multa por atraso ficam no contrato (advogado).

Sheet Escolas técnicas
A1: Escolas técnicas parceiras
A2: Primeira linha é um EXEMPLO inventado. Preencha as seguintes, uma escola por linha. Comissão por aluno é fórmula.
A4: Instituição | B4: Cidade e UF | C4: Curso | D4: Modalidade | E4: Matrícula (R$) | F4: Mensalidade (R$) | G4: Comissão sobre a matrícula | H4: Comissão sobre a mensalidade | I4: Comissão por aluno (R$) | J4: Credenciamento conferido? | K4: Contato | L4: Situação | M4: Observação
A5: EXEMPLO: Escola Técnica Modelo (inventada) | B5: Cidade Exemplo, UF | C5: Técnico em Eletrotécnica | D5: Presencial | E5: 300 | F5: 450 | G5: =Parcerias!$B$5 -> 0.5 | H5: =Parcerias!$B$6 -> 0.3 | I5: =IF(OR(E5="",F5=""),"",E5*G5+F5*H5*Parcerias!$B$7) -> 1770 | J5: Sim | K5: Pessoa Exemplo, (00) 00000-0000 | L5: Conversando | M5: Linha de exemplo; pode apagar.
A6: Centec (citado pelo GD) | C6: Elétrica, eletrônica, mecânica e mecânica de moto (citados pelo GD) | G6: =Parcerias!$B$5 -> 0.5 | H6: =Parcerias!$B$6 -> 0.3 | I6: =IF(OR(E6="",F6=""),"",E6*G6+F6*H6*Parcerias!$B$7) | L6: Não contatada | M6: Dados a confirmar: cidade, valores e credenciamento. Eu não abri o site.
G7: =Parcerias!$B$5 -> 0.5 | H7: =Parcerias!$B$6 -> 0.3 | I7: =IF(OR(E7="",F7=""),"",E7*G7+F7*H7*Parcerias!$B$7)
G8: =Parcerias!$B$5 -> 0.5 | H8: =Parcerias!$B$6 -> 0.3 | I8: =IF(OR(E8="",F8=""),"",E8*G8+F8*H8*Parcerias!$B$7)
G9: =Parcerias!$B$5 -> 0.5 | H9: =Parcerias!$B$6 -> 0.3 | I9: =IF(OR(E9="",F9=""),"",E9*G9+F9*H9*Parcerias!$B$7)
G10: =Parcerias!$B$5 -> 0.5 | H10: =Parcerias!$B$6 -> 0.3 | I10: =IF(OR(E10="",F10=""),"",E10*G10+F10*H10*Parcerias!$B$7)
G11: =Parcerias!$B$5 -> 0.5 | H11: =Parcerias!$B$6 -> 0.3 | I11: =IF(OR(E11="",F11=""),"",E11*G11+F11*H11*Parcerias!$B$7)
G12: =Parcerias!$B$5 -> 0.5 | H12: =Parcerias!$B$6 -> 0.3 | I12: =IF(OR(E12="",F12=""),"",E12*G12+F12*H12*Parcerias!$B$7)
G13: =Parcerias!$B$5 -> 0.5 | H13: =Parcerias!$B$6 -> 0.3 | I13: =IF(OR(E13="",F13=""),"",E13*G13+F13*H13*Parcerias!$B$7)
G14: =Parcerias!$B$5 -> 0.5 | H14: =Parcerias!$B$6 -> 0.3 | I14: =IF(OR(E14="",F14=""),"",E14*G14+F14*H14*Parcerias!$B$7)
G15: =Parcerias!$B$5 -> 0.5 | H15: =Parcerias!$B$6 -> 0.3 | I15: =IF(OR(E15="",F15=""),"",E15*G15+F15*H15*Parcerias!$B$7)
G16: =Parcerias!$B$5 -> 0.5 | H16: =Parcerias!$B$6 -> 0.3 | I16: =IF(OR(E16="",F16=""),"",E16*G16+F16*H16*Parcerias!$B$7)
G17: =Parcerias!$B$5 -> 0.5 | H17: =Parcerias!$B$6 -> 0.3 | I17: =IF(OR(E17="",F17=""),"",E17*G17+F17*H17*Parcerias!$B$7)
G18: =Parcerias!$B$5 -> 0.5 | H18: =Parcerias!$B$6 -> 0.3 | I18: =IF(OR(E18="",F18=""),"",E18*G18+F18*H18*Parcerias!$B$7)

Sheet Faculdades
A1: Faculdades e universidades parceiras
A2: Primeira linha é um EXEMPLO inventado. Preencha as seguintes, uma instituição por linha. Comissão por aluno é fórmula.
A4: Instituição | B4: Cidade e UF | C4: Curso | D4: Modalidade | E4: Matrícula (R$) | F4: Mensalidade (R$) | G4: Comissão sobre a matrícula | H4: Comissão sobre a mensalidade | I4: Comissão por aluno (R$) | J4: Credenciamento conferido? | K4: Contato | L4: Situação | M4: Observação
A5: EXEMPLO: Faculdade Modelo (inventada) | B5: Cidade Exemplo, UF | C5: Administração (graduação) | D5: EAD | E5: 250 | F5: 380 | G5: =Parcerias!$B$5 -> 0.5 | H5: =Parcerias!$B$6 -> 0.3 | I5: =IF(OR(E5="",F5=""),"",E5*G5+F5*H5*Parcerias!$B$7) -> 1493 | J5: Sim | K5: Pessoa Exemplo, (00) 00000-0000 | L5: Proposta enviada | M5: Linha de exemplo; pode apagar.
G6: =Parcerias!$B$5 -> 0.5 | H6: =Parcerias!$B$6 -> 0.3 | I6: =IF(OR(E6="",F6=""),"",E6*G6+F6*H6*Parcerias!$B$7)
G7: =Parcerias!$B$5 -> 0.5 | H7: =Parcerias!$B$6 -> 0.3 | I7: =IF(OR(E7="",F7=""),"",E7*G7+F7*H7*Parcerias!$B$7)
G8: =Parcerias!$B$5 -> 0.5 | H8: =Parcerias!$B$6 -> 0.3 | I8: =IF(OR(E8="",F8=""),"",E8*G8+F8*H8*Parcerias!$B$7)
G9: =Parcerias!$B$5 -> 0.5 | H9: =Parcerias!$B$6 -> 0.3 | I9: =IF(OR(E9="",F9=""),"",E9*G9+F9*H9*Parcerias!$B$7)
G10: =Parcerias!$B$5 -> 0.5 | H10: =Parcerias!$B$6 -> 0.3 | I10: =IF(OR(E10="",F10=""),"",E10*G10+F10*H10*Parcerias!$B$7)
G11: =Parcerias!$B$5 -> 0.5 | H11: =Parcerias!$B$6 -> 0.3 | I11: =IF(OR(E11="",F11=""),"",E11*G11+F11*H11*Parcerias!$B$7)
G12: =Parcerias!$B$5 -> 0.5 | H12: =Parcerias!$B$6 -> 0.3 | I12: =IF(OR(E12="",F12=""),"",E12*G12+F12*H12*Parcerias!$B$7)
G13: =Parcerias!$B$5 -> 0.5 | H13: =Parcerias!$B$6 -> 0.3 | I13: =IF(OR(E13="",F13=""),"",E13*G13+F13*H13*Parcerias!$B$7)
G14: =Parcerias!$B$5 -> 0.5 | H14: =Parcerias!$B$6 -> 0.3 | I14: =IF(OR(E14="",F14=""),"",E14*G14+F14*H14*Parcerias!$B$7)
G15: =Parcerias!$B$5 -> 0.5 | H15: =Parcerias!$B$6 -> 0.3 | I15: =IF(OR(E15="",F15=""),"",E15*G15+F15*H15*Parcerias!$B$7)
G16: =Parcerias!$B$5 -> 0.5 | H16: =Parcerias!$B$6 -> 0.3 | I16: =IF(OR(E16="",F16=""),"",E16*G16+F16*H16*Parcerias!$B$7)
G17: =Parcerias!$B$5 -> 0.5 | H17: =Parcerias!$B$6 -> 0.3 | I17: =IF(OR(E17="",F17=""),"",E17*G17+F17*H17*Parcerias!$B$7)

Sheet Cursos com parceiros
A1: Cursos que queremos com escola parceira
A2: Técnicos (diploma da escola) e mistos (teoria nossa, prática com parceiro). Coloque o parceiro na coluna amarela quando houver.
A4: Nº | B4: Setor | C4: Curso | D4: Tipo | E4: Horas-alvo | F4: Quem emite o documento | G4: Parceiro | H4: Situação
A5: 1 | B5: Gestão e carreira | C5: Libras básico | D5: Misto (teoria nossa, prática com parceiro) | E5: 10 | F5: Vem Trabalhar (certificado) + parceiro confirma a prática | H5: Sem parceiro
A6: 2 | B6: Turismo e gastronomia | C6: Auxiliar de cozinha | D6: Misto (teoria nossa, prática com parceiro) | E6: 20 | F6: Vem Trabalhar (certificado) + parceiro confirma a prática | H6: Sem parceiro
A7: 3 | B7: Turismo e gastronomia | C7: Barista | D7: Misto (teoria nossa, prática com parceiro) | E7: 8 | F7: Vem Trabalhar (certificado) + parceiro confirma a prática | H7: Sem parceiro
A8: 4 | B8: Turismo e gastronomia | C8: Padaria e confeitaria básica | D8: Misto (teoria nossa, prática com parceiro) | E8: 20 | F8: Vem Trabalhar (certificado) + parceiro confirma a prática | H8: Sem parceiro
A9: 5 | B9: Turismo e gastronomia | C9: Pizzaiolo e churrasqueiro | D9: Misto (teoria nossa, prática com parceiro) | E9: 20 | F9: Vem Trabalhar (certificado) + parceiro confirma a prática | H9: Sem parceiro
A10: 6 | B10: Turismo e gastronomia | C10: Bartender | D10: Misto (teoria nossa, prática com parceiro) | E10: 12 | F10: Vem Trabalhar (certificado) + parceiro confirma a prática | H10: Sem parceiro
A11: 7 | B11: Indústria | C11: Metrologia básica (paquímetro e micrômetro) | D11: Misto (teoria nossa, prática com parceiro) | E11: 10 | F11: Vem Trabalhar (certificado) + parceiro confirma a prática | H11: Sem parceiro
A12: 8 | B12: Indústria | C12: Operador de empilhadeira | D12: Técnico (escola parceira) | E12: 40 | F12: Escola credenciada (diploma técnico) | H12: Sem parceiro
A13: 9 | B13: Indústria | C13: Eletricista (curso técnico) | D13: Técnico (escola parceira) | E13: escola define | F13: Escola credenciada (diploma técnico) | H13: Sem parceiro
A14: 10 | B14: Indústria | C14: Eletrônica (curso técnico) | D14: Técnico (escola parceira) | E14: escola define | F14: Escola credenciada (diploma técnico) | H14: Sem parceiro
A15: 11 | B15: Indústria | C15: Mecânica de motos | D15: Técnico (escola parceira) | E15: escola define | F15: Escola credenciada (diploma técnico) | H15: Sem parceiro
A16: 12 | B16: Indústria | C16: Mecânica automotiva básica | D16: Técnico (escola parceira) | E16: escola define | F16: Escola credenciada (diploma técnico) | H16: Sem parceiro
A17: 13 | B17: Indústria | C17: Soldagem | D17: Técnico (escola parceira) | E17: escola define | F17: Escola credenciada (diploma técnico) | H17: Sem parceiro
A18: 14 | B18: Indústria | C18: Manutenção industrial | D18: Técnico (escola parceira) | E18: escola define | F18: Escola credenciada (diploma técnico) | H18: Sem parceiro
A19: 15 | B19: Indústria | C19: Operador de máquinas CNC | D19: Técnico (escola parceira) | E19: escola define | F19: Escola credenciada (diploma técnico) | H19: Sem parceiro
A20: 16 | B20: Indústria | C20: Costura industrial | D20: Misto (teoria nossa, prática com parceiro) | E20: 30 | F20: Vem Trabalhar (certificado) + parceiro confirma a prática | H20: Sem parceiro
A21: 17 | B21: Saúde e cuidados | C21: Técnico de enfermagem | D21: Técnico (escola parceira) | E21: escola define | F21: Escola credenciada (diploma técnico) | H21: Sem parceiro
A22: 18 | B22: Saúde e cuidados | C22: Técnico em saúde bucal | D22: Técnico (escola parceira) | E22: escola define | F22: Escola credenciada (diploma técnico) | H22: Sem parceiro
A23: 19 | B23: Saúde e cuidados | C23: Atendente de farmácia | D23: Técnico (escola parceira) | E23: escola define | F23: Escola credenciada (diploma técnico) | H23: Sem parceiro
A24: 20 | B24: Saúde e cuidados | C24: Cuidador de idosos | D24: Misto (teoria nossa, prática com parceiro) | E24: 40 | F24: Vem Trabalhar (certificado) + parceiro confirma a prática | H24: Sem parceiro
A25: 21 | B25: Saúde e cuidados | C25: Primeiros socorros no trabalho | D25: Misto (teoria nossa, prática com parceiro) | E25: 8 | F25: Vem Trabalhar (certificado) + parceiro confirma a prática | H25: Sem parceiro
A26: 22 | B26: Agro | C26: Apicultura básica | D26: Misto (teoria nossa, prática com parceiro) | E26: 12 | F26: Vem Trabalhar (certificado) + parceiro confirma a prática | H26: Sem parceiro
A27: 23 | B27: Agro | C27: Piscicultura básica | D27: Misto (teoria nossa, prática com parceiro) | E27: 12 | F27: Vem Trabalhar (certificado) + parceiro confirma a prática | H27: Sem parceiro
A28: 24 | B28: Agro | C28: Agroindústria artesanal (queijo, doces) | D28: Misto (teoria nossa, prática com parceiro) | E28: 12 | F28: Vem Trabalhar (certificado) + parceiro confirma a prática | H28: Sem parceiro
A29: 25 | B29: Agro | C29: Operador de máquinas agrícolas | D29: Técnico (escola parceira) | E29: escola define | F29: Escola credenciada (diploma técnico) | H29: Sem parceiro
A30: 26 | B30: Construção | C30: Pintura de parede | D30: Misto (teoria nossa, prática com parceiro) | E30: 12 | F30: Vem Trabalhar (certificado) + parceiro confirma a prática | H30: Sem parceiro
A31: 27 | B31: Construção | C31: Instalação hidráulica básica | D31: Misto (teoria nossa, prática com parceiro) | E31: 20 | F31: Vem Trabalhar (certificado) + parceiro confirma a prática | H31: Sem parceiro
A32: 28 | B32: Construção | C32: Eletricista predial | D32: Técnico (escola parceira) | E32: escola define | F32: Escola credenciada (diploma técnico) | H32: Sem parceiro
A33: 29 | B33: Construção | C33: Pedreiro de acabamento | D33: Misto (teoria nossa, prática com parceiro) | E33: 40 | F33: Vem Trabalhar (certificado) + parceiro confirma a prática | H33: Sem parceiro
A34: 30 | B34: Técnico e tecnologia | C34: Suporte técnico em informática | D34: Misto (teoria nossa, prática com parceiro) | E34: 20 | F34: Vem Trabalhar (certificado) + parceiro confirma a prática | H34: Sem parceiro
A35: 31 | B35: Técnico e tecnologia | C35: Redes de computadores (curso técnico) | D35: Técnico (escola parceira) | E35: escola define | F35: Escola credenciada (diploma técnico) | H35: Sem parceiro

Sheet Ideias de cursos
A1: Cursos livres nossos: ideias
A2: Só cursos livres, feitos por nós, com certificado de curso livre. As colunas das regiões leem a aba Prioridade. Técnicos e mistos estão na aba Cursos com parceiros.
B3: Ideias de cursos livres | C3: =COUNTA(C8:C300) -> 71
B4: Meta de cursos | C4: 200
B5: Falta para a meta (parcerias somam por fora) | C5: =MAX(0,C4-C3) -> 129
A7: Nº | B7: Setor | C7: Curso | D7: Horas-alvo | E7: Atividade de toque | F7: Norte | G7: Nordeste | H7: Centro-Oeste | I7: Sudeste | J7: Sul
A8: 1 | B8: Comércio e serviços | C8: Atendimento de balcão | D8: 6 | E8: Simulador: escolha a resposta ao cliente | F8: =INDEX(Prioridade!$B$5:$J$9,MATCH(F$7,Prioridade!$A$5:$A$9,0),MATCH($B8,Prioridade!$B$4:$J$4,0)) -> Média | G8: =INDEX(Prioridade!$B$5:$J$9,MATCH(G$7,Prioridade!$A$5:$A$9,0),MATCH($B8,Prioridade!$B$4:$J$4,0)) -> Alta | H8: =INDEX(Prioridade!$B$5:$J$9,MATCH(H$7,Prioridade!$A$5:$A$9,0),MATCH($B8,Prioridade!$B$4:$J$4,0)) -> Média | I8: =INDEX(Prioridade!$B$5:$J$9,MATCH(I$7,Prioridade!$A$5:$A$9,0),MATCH($B8,Prioridade!$B$4:$J$4,0)) -> Alta | J8: =INDEX(Prioridade!$B$5:$J$9,MATCH(J$7,Prioridade!$A$5:$A$9,0),MATCH($B8,Prioridade!$B$4:$J$4,0)) -> Média
A9: 2 | B9: Comércio e serviços | C9: Operador de caixa | D9: 8 | E9: Contar o troco arrastando notas e moedas | F9: =INDEX(Prioridade!$B$5:$J$9,MATCH(F$7,Prioridade!$A$5:$A$9,0),MATCH($B9,Prioridade!$B$4:$J$4,0)) -> Média | G9: =INDEX(Prioridade!$B$5:$J$9,MATCH(G$7,Prioridade!$A$5:$A$9,0),MATCH($B9,Prioridade!$B$4:$J$4,0)) -> Alta | H9: =INDEX(Prioridade!$B$5:$J$9,MATCH(H$7,Prioridade!$A$5:$A$9,0),MATCH($B9,Prioridade!$B$4:$J$4,0)) -> Média | I9: =INDEX(Prioridade!$B$5:$J$9,MATCH(I$7,Prioridade!$A$5:$A$9,0),MATCH($B9,Prioridade!$B$4:$J$4,0)) -> Alta | J9: =INDEX(Prioridade!$B$5:$J$9,MATCH(J$7,Prioridade!$A$5:$A$9,0),MATCH($B9,Prioridade!$B$4:$J$4,0)) -> Média
A10: 3 | B10: Comércio e serviços | C10: Atendimento ao cliente por WhatsApp | D10: 4 | E10: Ordenar mensagens e escolher o tom | F10: =INDEX(Prioridade!$B$5:$J$9,MATCH(F$7,Prioridade!$A$5:$A$9,0),MATCH($B10,Prioridade!$B$4:$J$4,0)) -> Média | G10: =INDEX(Prioridade!$B$5:$J$9,MATCH(G$7,Prioridade!$A$5:$A$9,0),MATCH($B10,Prioridade!$B$4:$J$4,0)) -> Alta | H10: =INDEX(Prioridade!$B$5:$J$9,MATCH(H$7,Prioridade!$A$5:$A$9,0),MATCH($B10,Prioridade!$B$4:$J$4,0)) -> Média | I10: =INDEX(Prioridade!$B$5:$J$9,MATCH(I$7,Prioridade!$A$5:$A$9,0),MATCH($B10,Prioridade!$B$4:$J$4,0)) -> Alta | J10: =INDEX(Prioridade!$B$5:$J$9,MATCH(J$7,Prioridade!$A$5:$A$9,0),MATCH($B10,Prioridade!$B$4:$J$4,0)) -> Média
A11: 4 | B11: Comércio e serviços | C11: Vendas para quem está começando | D11: 8 | E11: Role-play: contornar uma objeção | F11: =INDEX(Prioridade!$B$5:$J$9,MATCH(F$7,Prioridade!$A$5:$A$9,0),MATCH($B11,Prioridade!$B$4:$J$4,0)) -> Média | G11: =INDEX(Prioridade!$B$5:$J$9,MATCH(G$7,Prioridade!$A$5:$A$9,0),MATCH($B11,Prioridade!$B$4:$J$4,0)) -> Alta | H11: =INDEX(Prioridade!$B$5:$J$9,MATCH(H$7,Prioridade!$A$5:$A$9,0),MATCH($B11,Prioridade!$B$4:$J$4,0)) -> Média | I11: =INDEX(Prioridade!$B$5:$J$9,MATCH(I$7,Prioridade!$A$5:$A$9,0),MATCH($B11,Prioridade!$B$4:$J$4,0)) -> Alta | J11: =INDEX(Prioridade!$B$5:$J$9,MATCH(J$7,Prioridade!$A$5:$A$9,0),MATCH($B11,Prioridade!$B$4:$J$4,0)) -> Média
A12: 5 | B12: Comércio e serviços | C12: Atendimento por telefone | D12: 4 | E12: Escolher a frase certa em cada ligação | F12: =INDEX(Prioridade!$B$5:$J$9,MATCH(F$7,Prioridade!$A$5:$A$9,0),MATCH($B12,Prioridade!$B$4:$J$4,0)) -> Média | G12: =INDEX(Prioridade!$B$5:$J$9,MATCH(G$7,Prioridade!$A$5:$A$9,0),MATCH($B12,Prioridade!$B$4:$J$4,0)) -> Alta | H12: =INDEX(Prioridade!$B$5:$J$9,MATCH(H$7,Prioridade!$A$5:$A$9,0),MATCH($B12,Prioridade!$B$4:$J$4,0)) -> Média | I12: =INDEX(Prioridade!$B$5:$J$9,MATCH(I$7,Prioridade!$A$5:$A$9,0),MATCH($B12,Prioridade!$B$4:$J$4,0)) -> Alta | J12: =INDEX(Prioridade!$B$5:$J$9,MATCH(J$7,Prioridade!$A$5:$A$9,0),MATCH($B12,Prioridade!$B$4:$J$4,0)) -> Média
A13: 6 | B13: Comércio e serviços | C13: Como lidar com cliente difícil | D13: 3 | E13: Escolher o caminho em histórias curtas | F13: =INDEX(Prioridade!$B$5:$J$9,MATCH(F$7,Prioridade!$A$5:$A$9,0),MATCH($B13,Prioridade!$B$4:$J$4,0)) -> Média | G13: =INDEX(Prioridade!$B$5:$J$9,MATCH(G$7,Prioridade!$A$5:$A$9,0),MATCH($B13,Prioridade!$B$4:$J$4,0)) -> Alta | H13: =INDEX(Prioridade!$B$5:$J$9,MATCH(H$7,Prioridade!$A$5:$A$9,0),MATCH($B13,Prioridade!$B$4:$J$4,0)) -> Média | I13: =INDEX(Prioridade!$B$5:$J$9,MATCH(I$7,Prioridade!$A$5:$A$9,0),MATCH($B13,Prioridade!$B$4:$J$4,0)) -> Alta | J13: =INDEX(Prioridade!$B$5:$J$9,MATCH(J$7,Prioridade!$A$5:$A$9,0),MATCH($B13,Prioridade!$B$4:$J$4,0)) -> Média
A14: 7 | B14: Comércio e serviços | C14: Organização e reposição de loja | D14: 5 | E14: Arrastar produtos para a prateleira certa | F14: =INDEX(Prioridade!$B$5:$J$9,MATCH(F$7,Prioridade!$A$5:$A$9,0),MATCH($B14,Prioridade!$B$4:$J$4,0)) -> Média | G14: =INDEX(Prioridade!$B$5:$J$9,MATCH(G$7,Prioridade!$A$5:$A$9,0),MATCH($B14,Prioridade!$B$4:$J$4,0)) -> Alta | H14: =INDEX(Prioridade!$B$5:$J$9,MATCH(H$7,Prioridade!$A$5:$A$9,0),MATCH($B14,Prioridade!$B$4:$J$4,0)) -> Média | I14: =INDEX(Prioridade!$B$5:$J$9,MATCH(I$7,Prioridade!$A$5:$A$9,0),MATCH($B14,Prioridade!$B$4:$J$4,0)) -> Alta | J14: =INDEX(Prioridade!$B$5:$J$9,MATCH(J$7,Prioridade!$A$5:$A$9,0),MATCH($B14,Prioridade!$B$4:$J$4,0)) -> Média
A15: 8 | B15: Comércio e serviços | C15: Controle de estoque simples | D15: 6 | E15: Contar e conferir a lista | F15: =INDEX(Prioridade!$B$5:$J$9,MATCH(F$7,Prioridade!$A$5:$A$9,0),MATCH($B15,Prioridade!$B$4:$J$4,0)) -> Média | G15: =INDEX(Prioridade!$B$5:$J$9,MATCH(G$7,Prioridade!$A$5:$A$9,0),MATCH($B15,Prioridade!$B$4:$J$4,0)) -> Alta | H15: =INDEX(Prioridade!$B$5:$J$9,MATCH(H$7,Prioridade!$A$5:$A$9,0),MATCH($B15,Prioridade!$B$4:$J$4,0)) -> Média | I15: =INDEX(Prioridade!$B$5:$J$9,MATCH(I$7,Prioridade!$A$5:$A$9,0),MATCH($B15,Prioridade!$B$4:$J$4,0)) -> Alta | J15: =INDEX(Prioridade!$B$5:$J$9,MATCH(J$7,Prioridade!$A$5:$A$9,0),MATCH($B15,Prioridade!$B$4:$J$4,0)) -> Média
A16: 9 | B16: Comércio e serviços | C16: Vender pelas redes sociais | D16: 6 | E16: Montar uma postagem de venda | F16: =INDEX(Prioridade!$B$5:$J$9,MATCH(F$7,Prioridade!$A$5:$A$9,0),MATCH($B16,Prioridade!$B$4:$J$4,0)) -> Média | G16: =INDEX(Prioridade!$B$5:$J$9,MATCH(G$7,Prioridade!$A$5:$A$9,0),MATCH($B16,Prioridade!$B$4:$J$4,0)) -> Alta | H16: =INDEX(Prioridade!$B$5:$J$9,MATCH(H$7,Prioridade!$A$5:$A$9,0),MATCH($B16,Prioridade!$B$4:$J$4,0)) -> Média | I16: =INDEX(Prioridade!$B$5:$J$9,MATCH(I$7,Prioridade!$A$5:$A$9,0),MATCH($B16,Prioridade!$B$4:$J$4,0)) -> Alta | J16: =INDEX(Prioridade!$B$5:$J$9,MATCH(J$7,Prioridade!$A$5:$A$9,0),MATCH($B16,Prioridade!$B$4:$J$4,0)) -> Média
A17: 10 | B17: Comércio e serviços | C17: Foto de produto com o celular | D17: 4 | E17: Comparar fotos boas e ruins | F17: =INDEX(Prioridade!$B$5:$J$9,MATCH(F$7,Prioridade!$A$5:$A$9,0),MATCH($B17,Prioridade!$B$4:$J$4,0)) -> Média | G17: =INDEX(Prioridade!$B$5:$J$9,MATCH(G$7,Prioridade!$A$5:$A$9,0),MATCH($B17,Prioridade!$B$4:$J$4,0)) -> Alta | H17: =INDEX(Prioridade!$B$5:$J$9,MATCH(H$7,Prioridade!$A$5:$A$9,0),MATCH($B17,Prioridade!$B$4:$J$4,0)) -> Média | I17: =INDEX(Prioridade!$B$5:$J$9,MATCH(I$7,Prioridade!$A$5:$A$9,0),MATCH($B17,Prioridade!$B$4:$J$4,0)) -> Alta | J17: =INDEX(Prioridade!$B$5:$J$9,MATCH(J$7,Prioridade!$A$5:$A$9,0),MATCH($B17,Prioridade!$B$4:$J$4,0)) -> Média
A18: 11 | B18: Comércio e serviços | C18: Marketing e publicidade para pequenos negócios | D18: 10 | E18: Montar uma campanha em 3 passos | F18: =INDEX(Prioridade!$B$5:$J$9,MATCH(F$7,Prioridade!$A$5:$A$9,0),MATCH($B18,Prioridade!$B$4:$J$4,0)) -> Média | G18: =INDEX(Prioridade!$B$5:$J$9,MATCH(G$7,Prioridade!$A$5:$A$9,0),MATCH($B18,Prioridade!$B$4:$J$4,0)) -> Alta | H18: =INDEX(Prioridade!$B$5:$J$9,MATCH(H$7,Prioridade!$A$5:$A$9,0),MATCH($B18,Prioridade!$B$4:$J$4,0)) -> Média | I18: =INDEX(Prioridade!$B$5:$J$9,MATCH(I$7,Prioridade!$A$5:$A$9,0),MATCH($B18,Prioridade!$B$4:$J$4,0)) -> Alta | J18: =INDEX(Prioridade!$B$5:$J$9,MATCH(J$7,Prioridade!$A$5:$A$9,0),MATCH($B18,Prioridade!$B$4:$J$4,0)) -> Média
A19: 12 | B19: Comércio e serviços | C19: Instagram para negócios | D19: 6 | E19: Escolher legenda e horário | F19: =INDEX(Prioridade!$B$5:$J$9,MATCH(F$7,Prioridade!$A$5:$A$9,0),MATCH($B19,Prioridade!$B$4:$J$4,0)) -> Média | G19: =INDEX(Prioridade!$B$5:$J$9,MATCH(G$7,Prioridade!$A$5:$A$9,0),MATCH($B19,Prioridade!$B$4:$J$4,0)) -> Alta | H19: =INDEX(Prioridade!$B$5:$J$9,MATCH(H$7,Prioridade!$A$5:$A$9,0),MATCH($B19,Prioridade!$B$4:$J$4,0)) -> Média | I19: =INDEX(Prioridade!$B$5:$J$9,MATCH(I$7,Prioridade!$A$5:$A$9,0),MATCH($B19,Prioridade!$B$4:$J$4,0)) -> Alta | J19: =INDEX(Prioridade!$B$5:$J$9,MATCH(J$7,Prioridade!$A$5:$A$9,0),MATCH($B19,Prioridade!$B$4:$J$4,0)) -> Média
... A78: 71 | B78: Técnico e tecnologia | C78: Criação de site simples | D78: 10 | E78: Montar uma página arrastando blocos | F78: =INDEX(Prioridade!$B$5:$J$9,MATCH(F$7,Prioridade!$A$5:$A$9,0),MATCH($B78,Prioridade!$B$4:$J$4,0)) -> Alta | G78: =INDEX(Prioridade!$B$5:$J$9,MATCH(G$7,Prioridade!$A$5:$A$9,0),MATCH($B78,Prioridade!$B$4:$J$4,0)) -> Média | H78: =INDEX(Prioridade!$B$5:$J$9,MATCH(H$7,Prioridade!$A$5:$A$9,0),MATCH($B78,Prioridade!$B$4:$J$4,0)) -> Média | I78: =INDEX(Prioridade!$B$5:$J$9,MATCH(I$7,Prioridade!$A$5:$A$9,0),MATCH($B78,Prioridade!$B$4:$J$4,0)) -> Alta | J78: =INDEX(Prioridade!$B$5:$J$9,MATCH(J$7,Prioridade!$A$5:$A$9,0),MATCH($B78,Prioridade!$B$4:$J$4,0)) -> Alta

Sheet Cursos próprios
A1: Como é um curso do Vem Trabalhar
A2: Curso livre feito por nós, com lições curtas, atividades de toque, reteste e prova final que dá certificado e nunca elimina.
A4: Parte | B4: Como é
A5: Tamanho | B5: De 3 a 20 horas por curso, em lições de 5 a 8 minutos. Cabe numa pausa e no 3G.
A6: Cada lição | B6: 1) texto curto (até 150 palavras) com figura; 2) áudio opcional com voz calma; 3) atividade de toque (arrastar, ordenar, escolher a resposta do cliente, contar o troco); 4) mini-pergunta.
A7: Reteste | B7: Perguntas que já erradas voltam em outro dia, com outra redação. Cada habilidade tem pelo menos 3 perguntas diferentes no banco.
A8: Prova final | B8: 10 a 20 perguntas sorteadas do banco. Nota mínima 70%. Pode refazer quantas vezes quiser, com perguntas novas. Nunca elimina ninguém.
A9: Certificado | B9: Certificado de conclusão de curso livre, em PDF, com código e QR para a empresa conferir. Não é diploma. Diploma técnico só uma escola credenciada pode emitir.
A10: Quem escreve | B10: A IA escreve o rascunho; uma pessoa revisa antes de publicar (conteúdo errado em curso é risco para nós).
A11: Melhoria contínua | B11: O app mede onde as pessoas erram e saem; a pergunta mais errada vira lição melhor. Cada curso tem versão e data da revisão.
A12: Funciona em rede ruim | B12: Lição baixa em poucos KB, texto primeiro, imagem leve, áudio só se a pessoa tocar. Continua de onde parou.
A13: Liga com o match | B13: Cada curso concluído soma habilidade e certificado no perfil. Na vaga, o app mostra: 'faça este curso e sua nota sobe de 62% para 74%'.
A14: O que não substitui | B14: Treinamentos que a lei exige de instituição credenciada (NR com carga e instrutor, CNH, cursos de conselhos como COREN) e curso técnico com diploma.

Sheet Canais
A1: Banco de pessoas vivo: 14 formas de entrar e de manter contato todo dia
A2: Regra de ouro: o banco só cresce com consentimento. Nada de lista comprada, nada de raspar Instagram. Custos a verificar antes de decidir.
A4: Nº | B4: Canal | C4: Como a pessoa entra no banco | D4: O que ela recebe ou faz todo dia | E4: Consentimento | F4: Custo (a verificar) | G4: Precisa de código? | H4: Pronto para 13/10? | I4: Cuidado
A5: 1 | B5: QR e link nos restaurantes do Vem Comer | C5: Cartaz na mesa e no balcão: 'Procura emprego? Toque aqui'. | D5: Vaga perto de onde a pessoa está. | E5: No cadastro, com caixa desmarcada. | F5: Impressão do cartaz | G5: Pouco | H5: Sim | I5: Só pôr o cartaz onde o dono do restaurante aceitar.
A6: 2 | B6: Link na bio e posts das páginas de vagas do Instagram | C6: Páginas parceiras (as mais de mil que o GD conhece) divulgam o link: 'Candidate-se com 1 toque'. | D6: Stories, posts e vagas novas. | E6: No cadastro. | F6: Acordo com cada página (permuta ou pagamento) | G6: Pouco | H6: Sim | I6: Não raspar dados do Instagram nem usar robô: a regra da rede proíbe. Só link.
A7: 3 | B7: WhatsApp: link de entrada e lista com aceite | C7: Toque em 'falar no WhatsApp' abre a conversa; a pessoa diz 'quero receber vagas'. | D7: Vagas novas, lição do dia, aviso de entrevista. | E7: Aceite escrito na conversa (opt-in). | F7: Verificar: a conta oficial cobra por mensagem enviada | G7: Pouco (entrada); muito (envio em massa) | H7: Parcial | I7: Usar só a conta oficial do WhatsApp; mensagem fora do aceite é bloqueio.
A8: 4 | B8: Notificação do app (PWA) | C8: A pessoa abre o app no celular e aceita receber avisos. | D8: Vaga com nota alta, lição do dia, prazo de curso. | E8: Permissão do próprio celular. | F8: Perto de zero | G8: Médio | H8: Não | I8: No iPhone o aviso só funciona com o app instalado na tela inicial (verificar a versão).
A9: 5 | B9: E-mail | C9: A pessoa informa o e-mail no cadastro. | D9: Resumo semanal de vagas e cursos. | E9: Caixa de aceite separada, com cancelamento em um toque. | F9: Baixo (verificar) | G9: Pouco | H9: Parcial | I9: Todo e-mail precisa de link para sair da lista.
A10: 6 | B10: SMS | C10: Código de entrada no cadastro. | D10: Código e aviso urgente (entrevista marcada). | E10: Aceite no cadastro. | F10: Por mensagem (verificar) | G10: Médio | H10: Não | I10: Só para o que é urgente; custa por mensagem.
A11: 7 | B11: Currículo em PDF com link e QR | C11: Cada currículo compartilhado leva 'Feito no Vem Trabalhar'. | D11: Quem recebe o currículo conhece o app. | E11: Quem abre o link se cadastra por conta própria. | F11: Perto de zero | G11: Muito | H11: Não | I11: A marca fica discreta e pode ser desligada num plano pago.
A12: 8 | B12: Indique um amigo | C12: Link de convite com código. | D12: Avisos de quando o amigo entra. | E12: O amigo aceita ao se cadastrar. | F12: Prêmio a definir | G12: Médio | H12: Não | I12: Prêmio em curso ou recurso do app, não em dinheiro, até o advogado ver.
A13: 9 | B13: Páginas públicas de vagas e cursos (Google) | C13: Busca no Google leva à vaga ou ao curso. | D13: - | E13: No cadastro. | F13: Perto de zero depois de pronto | G13: Muito | H13: Não | I13: Verificar se o Google exibe vagas no Brasil com esse tipo de marcação.
A14: 10 | B14: Lição do dia e sequência de dias | C14: Quem faz um curso livre ganha uma lição curta por dia. | D14: Uma lição de 5 a 8 minutos, com sequência de dias seguidos. | E14: Aceite de avisos. | F14: Perto de zero | G14: Muito | H14: Não | I14: A sequência incentiva o hábito, mas não pune a pessoa que falha.
A15: 11 | B15: Parceiros convidam alunos e ex-alunos | C15: Escola envia o link pelo portal do parceiro. | D15: Cursos e vagas ligadas ao curso dela. | E15: O aluno aceita ao se cadastrar. | F15: Zero (a escola faz) | G15: Médio | H15: Parcial | I15: Escola não envia lista de contatos para nós: o aluno entra pelo link.
A16: 12 | B16: Empresas convidam funcionários e candidatos | C16: Empresa envia o link para a equipe e para quem recebeu a vaga. | D16: Avaliação, cursos e vagas internas. | E16: O funcionário aceita e sabe que será avaliado. | F16: Zero (a empresa faz) | G16: Médio | H16: Não | I16: Funcionário vê o resultado dele; empresa não recebe o teste de perfil sem a autorização dele.
... A18: 14 | B18: Áudio no WhatsApp para fazer o currículo falando | C18: A pessoa manda áudios e recebe o currículo pronto. | D18: O currículo e as vagas que combinam. | E18: Aceite no começo da conversa. | F18: Verificar (transcrição e mensagens) | G18: Muito | H18: Não | I18: O áudio é dado pessoal: apagar depois de transcrever.
B20: Canais prontos para 13/10 | C20: =COUNTIF(H5:H18,"Sim") -> 3
B21: Parcialmente prontos | C21: =COUNTIF(H5:H18,"Parcial") -> 3
B22: Total de canais | C22: =COUNTA(B5:B18) -> 14
B24: O que o painel do dono mostra todo dia | C24: Para quê
B25: Pessoas que entraram hoje, por canal | C25: Saber qual canal funciona e onde parar de gastar.
B26: Quantas aceitaram receber avisos | C26: O banco útil é o que tem aceite.
B27: Quantas já têm currículo e quantas fizeram teste | C27: Medir se o cadastro vira perfil completo.
B28: Quantas fizeram a lição do dia e quantas voltaram | C28: Medir o hábito, que mantém o banco vivo.
B29: Vagas novas e candidatos por vaga | C29: Equilibrar os dois lados.
B30: Tempo até a primeira resposta de uma empresa | C30: Candidato sem resposta some do app.
B31: Matrículas e comissões do mês | C31: Acompanhar a receita das parcerias.

Sheet Sistema vivo
A1: Sistema vivo: agentes que propõem melhoria todo dia, e pessoas que decidem
A2: Agente propõe, gente decide. Nada vai ao ar sem os testes passarem e sem o GD aprovar a mudança.
A4: Agente | B4: O que faz | C4: Quando roda | D4: O que entrega | E4: Quem aprova | F4: Cuidado
A5: Benchmark | B5: Olha o que os concorrentes e o mercado de RH e de educação lançaram de novo e compara com o que temos. | C5: Toda semana | D5: Relatório curto com 3 ideias e o que custa fazer cada uma. | E5: GD | F5: Só informação pública; sem entrar em conta de ninguém.
A6: Cursos | B6: Vê onde os alunos erram e onde abandonam e propõe versão melhor do curso. | C6: Toda semana | D6: Lição reescrita e perguntas novas. | E6: Revisor humano | F6: A IA pode errar conteúdo: revisão antes de publicar.
A7: Vídeos | B7: Faz roteiro de vídeo curto a partir de cada curso e dica de carreira. | C7: Toda semana | D7: Roteiro e legenda prontos. | E7: GD | F7: Nada que prometa emprego nem fale de pessoa real.
A8: Qualidade do match | B8: Compara a nota prevista com quem foi contratado de verdade. | C8: Todo mês | D8: Proposta de novos pesos, com o antes e o depois. | E8: GD e advogado | F8: Nunca muda o peso sozinho; sem usar dado sensível.
A9: Comunicação | B9: Testa horários e textos de mensagem para quem aceitou receber. | C9: Contínuo | D9: Qual texto trouxe mais gente de volta. | E9: GD | F9: Só para quem deu aceite; respeitar o pedido de sair.
A10: Parcerias | B10: Lembra as escolas de atualizar cursos e vagas e confere a conta de comissão do mês. | C10: Todo mês | D10: Extrato por escola e pendências. | E10: GD | F10: Divergência vai para análise, não vira cobrança automática.
A11: Privacidade | B11: Atende pedido de apagar ou corrigir dados e confere se o aceite está em dia. | C11: Todo dia | D11: Lista do que foi atendido. | E11: Automático, com revisão do advogado | F11: Prazos da lei (a confirmar).
A12: Saúde do sistema | B12: Confere cópia de segurança, atualização e velocidade. | C12: Todo dia | D12: Aviso só se algo estiver errado. | E12: Automático | F12: Atualização automática com volta atrás é decisão pendente do GD.
A13: Currículos | B13: Vê se os modelos continuam sendo lidos pelos programas das empresas e propõe novos. | C13: Todo mês | D13: Modelos ajustados e testes. | E13: GD | F13: A nota de leitura automática hoje é nossa avaliação.
A15: Limites: cada agente tem teto de custo por mês (a definir) e só mexe no que está descrito. Mudança de código passa por pull request, testes e o seu aceite.

Sheet IA para o dono
A1: IA para cada dono que comprar o software: 3 pilares, por voz ou foto
A2: Benchmark do texto da V4 (colado pelo GD): conteúdo em escala, análise de dados e imagens profissionais. Aqui, como isso vira função em cada produto.
A4: Pilar | B4: O que o dono pede | C4: No Vem Comer | D4: No Vem Trabalhar | E4: Em cursos e currículo | F4: Regra de segurança | G4: Situação hoje
A5: 1. Conteúdo em escala: uma ideia vira 10 formatos | B5: 'Faz um post desse prato.' 'Divulga essa vaga.' | C5: Do prato saem: post, carrossel, story, texto de WhatsApp, cartaz com QR, roteiro de vídeo curto, e-mail, promoção, legenda e mensagem de aniversário. | D5: Da vaga saem: post, story, texto de WhatsApp, cartaz com QR, e-mail e vídeo curto, prontos para as páginas de vagas do Instagram. | E5: De uma lição saem vídeo curto, post e quiz. Do currículo sai a mensagem de apresentação para o WhatsApp. | F5: O dono aprova antes de publicar. Nada que prometa o que o negócio não entrega. Vaga nunca promete salário que não está cadastrado. | G5: A fazer
A6: 2. Analisar dados e decidir mais rápido | B6: 'Como foi a semana?' 'Onde estou perdendo dinheiro?' | C6: Prato com margem baixa (custo e CMV), desperdício, horário vazio, prato que não vende, preço fora do padrão. | D6: Vaga parada, candidatos por vaga, onde a nota perde pontos, tempo até a primeira resposta, saída de funcionários. | E6: Onde o aluno erra e onde desiste do curso. | F6: Todo número mostra de onde vem. A sugestão é sugestão: o dono decide. Resposta curta, em linguagem simples. | G6: A fazer (CMV é o item 6 e alertas o item 10 da ordem de trabalho)
A7: 3. Imagens profissionais | B7: 'Melhora essa foto.' 'Faz a logomarca.' 'Faz o cartaz da vaga.' | C7: Foto do prato melhorada a partir da foto real, com fundo limpo; logomarca; banner do cardápio. | D7: Imagem da vaga e cartaz com QR; capa de curso. | E7: Currículo sem foto de pessoa criada por IA. | F7: Foto de prato só melhora a real. Imagem criada do zero leva o aviso 'imagem ilustrativa' (o cliente não pode ser enganado sobre o que recebe; advogado confere o Código de Defesa do Consumidor). Nunca criar pessoa que não existe em currículo ou depoimento. | G7: Parcial: foto do cardápio pronta (falta a chave de IA e teste com cardápios reais); logomarca pronta (aguarda o seu merge)
A8: 4. Gestão por voz e por foto | B8: Falar ou mandar foto, em vez de digitar | C8: Ver a aba Comandos de voz. | D8: Ver a aba Comandos de voz. | E8: Ver a aba Entrevista do currículo. | F8: Ação que mexe com dinheiro, preço ou apaga algo sempre pede confirmação lida em voz alta, e pode ser desfeita. | G8: A fazer
A9: 5. Muitas empresas na mesma plataforma | B9: 'Cada cliente meu com a sua marca.' | C9: Cada restaurante isolado, com logomarca, cores e cardápio próprios. | D9: Cada empresa isolada, com vagas e candidatos próprios. | E9: Cada empresa vê só os seus funcionários e resultados. | F9: Uma empresa nunca enxerga dado de outra. O dono da plataforma enxerga números gerais, não o conteúdo de cada uma. | G9: Isolamento por empresa já existe. Logomarca pronta. Faltam domínio próprio e teste de Pix de R$ 1.

Sheet Comandos de voz
A1: Comandos de voz e de foto: o dono fala, o sistema faz
A2: Frases de exemplo. O sistema entende o jeito de falar de cada pessoa; estas servem para desenhar e testar.
A4: Nº | B4: Produto | C4: Quem fala | D4: O que diz | E4: O que o sistema faz | F4: Pede confirmação? | G4: Cuidado
A5: 1 | B5: Vem Comer | C5: Dono ou gerente | D5: Quanto eu vendi hoje? | E5: Lê as vendas, os pedidos e o ticket médio do dia. | F5: Não | G5: Número vem do sistema, com a hora da última atualização.
A6: 2 | B6: Vem Comer | C6: Dono ou gerente | D6: Qual prato vende mais esta semana? | E6: Lista os 5 mais vendidos e os 5 que menos saem. | F6: Não | G6: -
A7: 3 | B7: Vem Comer | C7: Dono ou gerente | D7: Coloca o prato frango com batata por R$ 25. | E7: Cria ou muda o produto e mostra o preço escrito. | F7: Sim | G7: Lê o preço em voz alta antes de salvar.
A8: 4 | B8: Vem Comer | C8: Dono ou gerente | D8: Tira o prato X do cardápio por hoje. | E8: Pausa o prato até a meia-noite. | F8: Sim | G8: Volta sozinho no dia seguinte.
A9: 5 | B9: Vem Comer | C9: Dono ou gerente | D9: Aumenta as bebidas em 10 por cento. | E9: Mostra a lista com o preço novo de cada bebida. | F9: Sim | G9: Aplica só depois do toque em 'confirmar'; tem 'desfazer'.
A10: 6 | B10: Vem Comer | C10: Dono ou gerente | D10: (manda uma foto de um prato) Esse é o prato do dia. | E10: Melhora a foto, cria o prato e pede o preço e a descrição. | F10: Sim | G10: Só melhora a foto real.
A11: 7 | B11: Vem Comer | C11: Dono ou gerente | D11: Faz um post desse prato. | E11: Gera post, story e texto de WhatsApp para aprovar. | F11: Sim | G11: Nada é publicado sem o dono aprovar.
A12: 8 | B12: Vem Comer | C12: Dono ou gerente | D12: Onde eu estou perdendo dinheiro? | E12: Mostra os 3 maiores vazamentos com o valor de cada um. | F12: Não | G12: Diz de onde vem cada número.
A13: 9 | B13: Vem Comer | C13: Garçom | D13: Mesa 5 quer mais uma água e um suco de laranja. | E13: Lança os itens na mesa 5. | F13: Sim | G13: Garçom não muda preço.
A14: 10 | B14: Vem Comer | C14: Caixa | D14: Fecha a mesa 3 no Pix. | E14: Fecha a conta e mostra o QR. | F14: Sim | G14: Só o caixa fecha.
A15: 11 | B15: Vem Comer | C15: Cozinha | D15: Pedido 12 está pronto. | E15: Marca como pronto e avisa o garçom. | F15: Não | G15: -
A16: 12 | B16: Vem Comer | C16: Dono ou gerente | D16: Cria uma promoção de almoço de segunda a sexta. | E16: Monta a promoção e o cartaz para aprovar. | F16: Sim | G16: Mostra o preço final antes de ligar.
... A36: 32 | B36: Dono da plataforma | C36: GD | D36: Quanto as escolas devem de comissão? | E36: Mostra o extrato por escola. | F36: Não | G36: Aba Portal do parceiro.
B38: Comandos | C38: =COUNTA(D5:D36) -> 32
B39: Pedem confirmação | C39: =COUNTIF(F5:F36,"Sim*") -> 13
B41: O reconhecimento de voz do celular pode precisar de internet; a verificar como fica em 2G. Se não houver rede, o sistema oferece os botões de toque.

Sheet Benchmark
A1: Benchmark: o que vimos de novo e onde entra
A2: O agente de benchmark da aba Sistema vivo acrescenta linhas aqui. A coluna amarela é a sua decisão.
A4: Data | B4: Onde vimos | C4: O que vimos | D4: O que serve para nós | E4: Onde entra | F4: Prioridade | G4: Decisão do GD
A5: 06/10/2026 | B5: Texto de uma empresa chamada V4 (colado pelo GD) | C5: Quem não usa IA em 3 coisas fica para trás: 1) conteúdo em escala, uma ideia vira 10 formatos; 2) análise de dados e decisão mais rápida; 3) imagens profissionais sem sessão de fotos. | D5: Os três pilares viram o que cada dono recebe, por voz ou foto (aba IA para o dono). | E5: Vem Comer, Vem Trabalhar, cursos, currículo | F5: Alta
A6: 06/10/2026 | B6: Anúncio no Instagram (print do GD): gentia.tech, '50 vagas rodando para 1 recrutador' | C6: Promessa de um recrutador dar conta de 50 vagas com IA. | D6: A lista ordenada com o motivo da nota e o match de 20 perguntas atacam a mesma dor. | E6: Vem Trabalhar | F6: Alta
A7: 06/10/2026 | B7: Sites de RH que o GD já viu (um anotado como 'Holdings Group'; o nome pode ser erro de transcrição) | C7: Segundo o GD, nenhum atende do autônomo até a empresa de mil funcionários com uma ideia só. É afirmação do GD; eu não verifiquei esses sites. | D7: O nosso diferencial: o mesmo método, as mesmas telas, qualquer tamanho de empresa. | E7: Vem Trabalhar | F7: Alta

Sheet Prioridade
A1: Prioridade de cursos por região e setor
A2: Alta, Média ou Baixa. É avaliação nossa, sem dados; toque na célula para mudar. A aba Ideias de cursos lê esta tabela.
A4: Região | B4: Indústria | C4: Agro | D4: Técnico e tecnologia | E4: Turismo e gastronomia | F4: Comércio e serviços | G4: Gestão e carreira | H4: Transporte e logística | I4: Saúde e cuidados | J4: Construção
A5: Norte | B5: Alta | C5: Média | D5: Alta | E5: Média | F5: Média | G5: Alta | H5: Média | I5: Média | J5: Média
A6: Nordeste | B6: Média | C6: Alta | D6: Média | E6: Alta | F6: Alta | G6: Alta | H6: Média | I6: Média | J6: Média
A7: Centro-Oeste | B7: Média | C7: Alta | D7: Média | E7: Média | F7: Média | G7: Alta | H7: Alta | I7: Média | J7: Média
A8: Sudeste | B8: Alta | C8: Média | D8: Alta | E8: Média | F8: Alta | G8: Alta | H8: Alta | I8: Média | J8: Média
A9: Sul | B9: Alta | C9: Alta | D9: Alta | E9: Média | F9: Média | G9: Alta | H9: Alta | I9: Média | J9: Média
A12: Setor | B12: De onde vem a avaliação
A13: Indústria | B13: Avaliação nossa: polo de Manaus no Norte, indústria forte no Sudeste e no Sul.
A14: Agro | B14: Avaliação nossa: soja no Centro-Oeste, agropecuária no Sul, cana e pecuária no Nordeste.
A15: Técnico e tecnologia | B15: Avaliação nossa: eletroeletrônica no Norte, energia eólica no Nordeste, serviços no Sudeste.
A16: Turismo e gastronomia | B16: Avaliação nossa: o Nordeste é o destino mais procurado nas viagens de verão.
A17: Comércio e serviços | B17: Avaliação nossa: serviços pesam em todas as regiões.
A18: Gestão e carreira | B18: Transversal: vale para todas as regiões.
A19: Transporte e logística | B19: Avaliação nossa, ligada ao escoamento da safra e da indústria.
A20: Saúde e cuidados | B20: Avaliação nossa, sem dado ainda: todas Média.
A21: Construção | B21: Avaliação nossa, sem dado ainda: todas Média.

Sheet Matching
A1: Matching: 20 perguntas ao candidato e 20 correspondentes na vaga
A2: Cada pergunta do candidato tem a sua gêmea na vaga. A regra diz como comparar (nota de 0 a 1) e o peso diz quanto vale. Pesos são ponto de partida: letra azul, pode mudar.
A4: Nº | B4: Bloco | C4: Tema | D4: Pergunta ao candidato (toque ou voz) | E4: Respostas do candidato | F4: Pergunta na vaga (empresa) | G4: Respostas da empresa | H4: Como compara (nota de 0 a 1) | I4: Se não combinar | J4: Peso (1 a 5)
A5: 1 | B5: A. Logística | C5: Local e deslocamento | D5: Onde você mora? E quanto tempo aceita gastar para chegar ao trabalho? Como você vai? | E5: Localização (CEP ou 'usar onde estou'); tempo: 15 / 30 / 45 / 60 / 90 min ou mais; meio: a pé, bicicleta, moto, ônibus, carro. | F5: Onde fica o posto de trabalho? A empresa dá transporte ou vale-transporte? | G5: CEP do local; transporte da empresa: sim / não; vale-transporte: sim / não. | H5: Tempo estimado de casa ao trabalho no meio escolhido (aba Geografia). Dentro do limite = 1; até 20% acima = 0,5; acima = 0. | I5: Filtro do candidato | J5: 5
A6: 2 | B6: A. Logística | C6: Modalidade | D6: Onde prefere trabalhar? (pode marcar mais de uma) | E6: Presencial; híbrido; de casa. | F6: A vaga é presencial, híbrida ou remota? | G6: Presencial; híbrida; remota. | H6: Vaga dentro do que a pessoa aceita = 1; híbrido contra presencial ou remoto = 0,5; fora = 0. | I6: Filtro do candidato | J6: 4
A7: 3 | B7: A. Logística | C7: Turno e escala | D7: Em quais turnos você pode trabalhar? | E7: Manhã; tarde; noite; madrugada; fins de semana; feriados; escala 12x36. | F7: Qual o turno e a escala da vaga? | G7: Os mesmos turnos, mais escala 12x36 e carga semanal. | H7: Todos os turnos da vaga cobertos = 1; parte coberta = 0,5; nenhum = 0. | I7: Filtro do candidato | J7: 5
A8: 4 | B8: A. Logística | C8: Tipo de contrato | D8: Que tipo de contrato você aceita? | E8: CLT; estágio; jovem aprendiz; temporário; diária ou freelancer; MEI ou PJ. | F8: Qual o tipo de contrato? | G8: CLT; estágio; jovem aprendiz; temporário; diária ou freelancer; MEI ou PJ. | H8: Contrato aceito pela pessoa = 1; senão 0. | I8: Filtro do candidato | J8: 4
A9: 5 | B9: A. Logística | C9: Salário e benefícios | D9: Quanto você precisa ganhar por mês? | E9: Faixas de toque (a combinar, ou escolher a faixa); benefícios que importam: vale-transporte, refeição, plano de saúde. | F9: Qual a faixa de salário e os benefícios? | G9: Faixa de salário; benefícios: vale-transporte, refeição, plano, comissão. | H9: Faixas se encontram = 1; vaga até 10% abaixo do que a pessoa precisa = 0,5; mais que isso = 0. | I9: Filtro do candidato | J9: 5
A10: 6 | B10: A. Logística | C10: Quando começar | D10: Quando você pode começar? | E10: Já; em 15 dias; em 30 dias; depois. | F10: Para quando a vaga precisa de alguém? | G10: Urgente; em 15 dias; em 30 dias; sem pressa. | H10: Pessoa começa até a data pedida = 1; atraso de até 15 dias = 0,5; mais = 0. | I10: Só pontua | J10: 2
A11: 7 | B11: A. Logística | C11: Estudo junto com o trabalho | D11: Quer estudar junto com o trabalho? Como? | E11: Não; a distância (EAD); presencial; os dois. Horários livres para estudar. | F11: A empresa apoia o estudo? | G11: Não; horário flexível; paga curso ou bolsa; tem curso interno. | H11: Quer estudar e a empresa apoia = 1; tanto faz = 0,5; querem coisas opostas = 0. Se o curso é presencial, entra a distância casa, estudo e trabalho (aba Geografia). | I11: Só pontua | J11: 2
A12: 8 | B12: B. Função e preparo | C12: Função desejada | D12: Que tipo de trabalho você procura? (fale ou escolha até 3) | E12: Busca por voz ou lista de ocupações, agrupada por área. | F12: Qual a função da vaga? | G12: A mesma lista de ocupações. | H12: Mesma função = 1; função da mesma família = 0,6; mesma área = 0,3; outra = 0. | I12: Só pontua | J12: 5
A13: 9 | B13: B. Função e preparo | C13: Experiência | D13: Quanto tempo de experiência você tem nessa função? | E13: Nenhuma; até 1 ano; 1 a 3 anos; 3 a 5 anos; mais de 5 anos. | F13: Qual experiência a vaga exige? A empresa treina quem não tem? | G13: Nenhuma; até 1 ano; 1 a 3; 3 a 5; mais de 5. Marcar 'treinamos'. | H13: Experiência igual ou maior = 1; um nível abaixo = 0,5; mais abaixo = 0. Se a empresa marcou 'treinamos', quem não tem experiência pontua 0,8. Primeiro emprego nunca é penalizado em vaga que aceita sem experiência. | I13: Obrigatória só se a empresa marcar | J13: 4
A14: 10 | B14: B. Função e preparo | C14: Escolaridade | D14: Até onde você estudou? | E14: Fundamental incompleto ou completo; médio incompleto ou completo; técnico; superior cursando ou completo; pós. | F14: Qual a escolaridade mínima? | G14: A mesma escala, mais 'aceita quem está cursando'. | H14: Nível igual ou maior = 1; cursando e a vaga aceita = 0,7; um nível abaixo = 0,4; mais abaixo = 0. | I14: Obrigatória só se a empresa marcar | J14: 3
A15: 11 | B15: B. Função e preparo | C15: Habilidades | D15: Marque até 5 coisas que você faz bem. | E15: Lista por área (atender, vender, cozinhar, operar caixa, organizar estoque, dirigir, consertar, desenhar, ensinar...). | F15: Marque até 5 habilidades essenciais para a vaga. | G15: A mesma lista. | H15: Quantas das habilidades da vaga a pessoa tem, dividido pelo total da vaga. | I15: Só pontua | J15: 5
A16: 12 | B16: B. Função e preparo | C16: Ferramentas e equipamentos | D16: Quais máquinas, programas ou equipamentos você sabe usar? | E16: Lista por área (caixa e maquininha, Excel, empilhadeira, forno, furadeira, WhatsApp comercial...). | F16: O que a pessoa vai usar no dia a dia? | G16: A mesma lista. | H16: Quantas das ferramentas da vaga a pessoa conhece, dividido pelo total. | I16: Só pontua | J16: 3
... A24: 20 | B24: C. Jeito de trabalhar | C24: Crescimento | D24: O que você busca agora? | E24: Aprender uma profissão; crescer na empresa; estabilidade; renda extra. | F24: O que a empresa oferece? | G24: Treinamento; plano de carreira; efetivação; renda extra. | H24: Igual = 1; parcial = 0,5; sem relação = 0. | I24: Só pontua | J24: 2
C25: Perguntas | D25: =COUNTA(C5:C24) -> 20
C26: Soma dos pesos | D26: =SUM(J5:J24) -> 68
C28: Filtro do candidato: a vaga some da lista dele quando contraria um 'não' que ele mesmo marcou. Quem decide é ele, não o sistema.
C29: Obrigatória só se a empresa marcar: a empresa pode marcar até 3 perguntas como obrigatórias. Quem não atende aparece com o aviso 'não atende' e a empresa decide se abre ou não. Nada é escondido da empresa nem descartado sozinho.
C30: Dado que a empresa deixa em branco não entra na conta (o peso daquele par sai do total).
C31: Sinal 21, opcional: o teste de jeito de ser (aba Perfil) só entra se a pessoa autorizar e a empresa pedir. Nunca elimina.
C32: A pessoa vê a nota, os 3 pares que mais tiraram pontos e o curso que melhoraria cada um.
C33: Raça, religião, estado civil, filhos, idade, foto e saúde não fazem parte de nenhum par.

Sheet Matching exemplo
A1: Exemplo de nota do matching (candidato e vaga inventados)
A2: Candidata de exemplo: procura balcão ou caixa, tem 1 ano de experiência, aceita CLT, pode à tarde e à noite. Vaga: atendente de padaria. Troque os números amarelos para ver a nota mudar.
B4: Obrigatória não atende abaixo de | C4: 0.5
B5: Faixa 'Muito boa' a partir de | C5: 0.8
B6: Faixa 'Boa' a partir de | C6: 0.6
B7: Faixa 'Possível' a partir de | C7: 0.4
A9: Nº | B9: Tema | C9: Peso | D9: Aplica? | E9: Nota (0 a 1) | F9: Obrigatória? | G9: Pontos | H9: Peso usado | I9: Perda (aux.) | J9: Alerta
A10: 1 | B10: =Matching!C5 -> Local e deslocamento | C10: =Matching!J5 -> 5 | D10: Sim | E10: 1 | F10: Não | G10: =IF(D10="Sim",C10*E10,0) -> 5 | H10: =IF(D10="Sim",C10,0) -> 5 | I10: =IF(D10="Sim",C10*(1-E10),0)+ROW()/1000000 -> 1e-05 | J10: =IF(AND(D10="Sim",F10="Sim",E10<$C$4),"Não atende","") | L10: Nota do match | M10: =IF(SUM(H10:H29)=0,"",SUM(G10:G29)/SUM(H10:H29)) -> 0.78225806
A11: 2 | B11: =Matching!C6 -> Modalidade | C11: =Matching!J6 -> 4 | D11: Sim | E11: 1 | F11: Não | G11: =IF(D11="Sim",C11*E11,0) -> 4 | H11: =IF(D11="Sim",C11,0) -> 4 | I11: =IF(D11="Sim",C11*(1-E11),0)+ROW()/1000000 -> 1.1e-05 | J11: =IF(AND(D11="Sim",F11="Sim",E11<$C$4),"Não atende","") | L11: Faixa | M11: =IF(M10="","",IF(M10>=$C$5,"Muito boa",IF(M10>=$C$6,"Boa",IF(M10>=$C$7,"Possível","Distante")))) -> Boa
A12: 3 | B12: =Matching!C7 -> Turno e escala | C12: =Matching!J7 -> 5 | D12: Sim | E12: 1 | F12: Não | G12: =IF(D12="Sim",C12*E12,0) -> 5 | H12: =IF(D12="Sim",C12,0) -> 5 | I12: =IF(D12="Sim",C12*(1-E12),0)+ROW()/1000000 -> 1.2e-05 | J12: =IF(AND(D12="Sim",F12="Sim",E12<$C$4),"Não atende","") | L12: Atende todas as obrigatórias? | M12: =IF(COUNTIF(J10:J29,"Não atende")=0,"Sim","Não") -> Sim
A13: 4 | B13: =Matching!C8 -> Tipo de contrato | C13: =Matching!J8 -> 4 | D13: Sim | E13: 1 | F13: Não | G13: =IF(D13="Sim",C13*E13,0) -> 4 | H13: =IF(D13="Sim",C13,0) -> 4 | I13: =IF(D13="Sim",C13*(1-E13),0)+ROW()/1000000 -> 1.3e-05 | J13: =IF(AND(D13="Sim",F13="Sim",E13<$C$4),"Não atende","")
A14: 5 | B14: =Matching!C9 -> Salário e benefícios | C14: =Matching!J9 -> 5 | D14: Sim | E14: 0.5 | F14: Não | G14: =IF(D14="Sim",C14*E14,0) -> 2.5 | H14: =IF(D14="Sim",C14,0) -> 5 | I14: =IF(D14="Sim",C14*(1-E14),0)+ROW()/1000000 -> 2.500014 | J14: =IF(AND(D14="Sim",F14="Sim",E14<$C$4),"Não atende","") | L14: Onde mais perdeu pontos (mostrar à pessoa)
A15: 6 | B15: =Matching!C10 -> Quando começar | C15: =Matching!J10 -> 2 | D15: Sim | E15: 1 | F15: Não | G15: =IF(D15="Sim",C15*E15,0) -> 2 | H15: =IF(D15="Sim",C15,0) -> 2 | I15: =IF(D15="Sim",C15*(1-E15),0)+ROW()/1000000 -> 1.5e-05 | J15: =IF(AND(D15="Sim",F15="Sim",E15<$C$4),"Não atende","") | L15: =IF(LARGE($I$10:$I$29,1)<0.001,"",INDEX($B$10:$B$29,MATCH(LARGE($I$10:$I$29,1),$I$10:$I$29,0))) -> Habilidades
A16: 7 | B16: =Matching!C11 -> Estudo junto com o trabalho | C16: =Matching!J11 -> 2 | D16: Sim | E16: 0.5 | F16: Não | G16: =IF(D16="Sim",C16*E16,0) -> 1 | H16: =IF(D16="Sim",C16,0) -> 2 | I16: =IF(D16="Sim",C16*(1-E16),0)+ROW()/1000000 -> 1.000016 | J16: =IF(AND(D16="Sim",F16="Sim",E16<$C$4),"Não atende","") | L16: =IF(LARGE($I$10:$I$29,2)<0.001,"",INDEX($B$10:$B$29,MATCH(LARGE($I$10:$I$29,2),$I$10:$I$29,0))) -> Salário e benefícios
A17: 8 | B17: =Matching!C12 -> Função desejada | C17: =Matching!J12 -> 5 | D17: Sim | E17: 1 | F17: Não | G17: =IF(D17="Sim",C17*E17,0) -> 5 | H17: =IF(D17="Sim",C17,0) -> 5 | I17: =IF(D17="Sim",C17*(1-E17),0)+ROW()/1000000 -> 1.7e-05 | J17: =IF(AND(D17="Sim",F17="Sim",E17<$C$4),"Não atende","") | L17: =IF(LARGE($I$10:$I$29,3)<0.001,"",INDEX($B$10:$B$29,MATCH(LARGE($I$10:$I$29,3),$I$10:$I$29,0))) -> Experiência
A18: 9 | B18: =Matching!C13 -> Experiência | C18: =Matching!J13 -> 4 | D18: Sim | E18: 0.5 | F18: Sim | G18: =IF(D18="Sim",C18*E18,0) -> 2 | H18: =IF(D18="Sim",C18,0) -> 4 | I18: =IF(D18="Sim",C18*(1-E18),0)+ROW()/1000000 -> 2.000018 | J18: =IF(AND(D18="Sim",F18="Sim",E18<$C$4),"Não atende","")
A19: 10 | B19: =Matching!C14 -> Escolaridade | C19: =Matching!J14 -> 3 | D19: Sim | E19: 1 | F19: Não | G19: =IF(D19="Sim",C19*E19,0) -> 3 | H19: =IF(D19="Sim",C19,0) -> 3 | I19: =IF(D19="Sim",C19*(1-E19),0)+ROW()/1000000 -> 1.9e-05 | J19: =IF(AND(D19="Sim",F19="Sim",E19<$C$4),"Não atende","") | L19: A coluna 'Perda (aux.)' soma uma fração minúscula da linha só para desempatar.
A20: 11 | B20: =Matching!C15 -> Habilidades | C20: =Matching!J15 -> 5 | D20: Sim | E20: 0.4 | F20: Não | G20: =IF(D20="Sim",C20*E20,0) -> 2 | H20: =IF(D20="Sim",C20,0) -> 5 | I20: =IF(D20="Sim",C20*(1-E20),0)+ROW()/1000000 -> 3.00002 | J20: =IF(AND(D20="Sim",F20="Sim",E20<$C$4),"Não atende","")
A21: 12 | B21: =Matching!C16 -> Ferramentas e equipamentos | C21: =Matching!J16 -> 3 | D21: Sim | E21: 0.5 | F21: Não | G21: =IF(D21="Sim",C21*E21,0) -> 1.5 | H21: =IF(D21="Sim",C21,0) -> 3 | I21: =IF(D21="Sim",C21*(1-E21),0)+ROW()/1000000 -> 1.500021 | J21: =IF(AND(D21="Sim",F21="Sim",E21<$C$4),"Não atende","")
A22: 13 | B22: =Matching!C17 -> Habilitações e certificados | C22: =Matching!J17 -> 4 | D22: Não | E22: 1 | F22: Não | G22: =IF(D22="Sim",C22*E22,0) -> 0 | H22: =IF(D22="Sim",C22,0) -> 0 | I22: =IF(D22="Sim",C22*(1-E22),0)+ROW()/1000000 -> 2.2e-05 | J22: =IF(AND(D22="Sim",F22="Sim",E22<$C$4),"Não atende","")
A23: 14 | B23: =Matching!C18 -> Idiomas | C23: =Matching!J18 -> 2 | D23: Não | E23: 1 | F23: Não | G23: =IF(D23="Sim",C23*E23,0) -> 0 | H23: =IF(D23="Sim",C23,0) -> 0 | I23: =IF(D23="Sim",C23*(1-E23),0)+ROW()/1000000 -> 2.3e-05 | J23: =IF(AND(D23="Sim",F23="Sim",E23<$C$4),"Não atende","")
A24: 15 | B24: =Matching!C19 -> Ambiente | C24: =Matching!J19 -> 3 | D24: Sim | E24: 1 | F24: Não | G24: =IF(D24="Sim",C24*E24,0) -> 3 | H24: =IF(D24="Sim",C24,0) -> 3 | I24: =IF(D24="Sim",C24*(1-E24),0)+ROW()/1000000 -> 2.4e-05 | J24: =IF(AND(D24="Sim",F24="Sim",E24<$C$4),"Não atende","")
A25: 16 | B25: =Matching!C20 -> Ritmo | C25: =Matching!J20 -> 3 | D25: Sim | E25: 0.5 | F25: Não | G25: =IF(D25="Sim",C25*E25,0) -> 1.5 | H25: =IF(D25="Sim",C25,0) -> 3 | I25: =IF(D25="Sim",C25*(1-E25),0)+ROW()/1000000 -> 1.500025 | J25: =IF(AND(D25="Sim",F25="Sim",E25<$C$4),"Não atende","")
A26: 17 | B26: =Matching!C21 -> Equipe | C26: =Matching!J21 -> 2 | D26: Sim | E26: 1 | F26: Não | G26: =IF(D26="Sim",C26*E26,0) -> 2 | H26: =IF(D26="Sim",C26,0) -> 2 | I26: =IF(D26="Sim",C26*(1-E26),0)+ROW()/1000000 -> 2.6e-05 | J26: =IF(AND(D26="Sim",F26="Sim",E26<$C$4),"Não atende","")
A27: 18 | B27: =Matching!C22 -> Contato com o público | C27: =Matching!J22 -> 3 | D27: Sim | E27: 1 | F27: Não | G27: =IF(D27="Sim",C27*E27,0) -> 3 | H27: =IF(D27="Sim",C27,0) -> 3 | I27: =IF(D27="Sim",C27*(1-E27),0)+ROW()/1000000 -> 2.7e-05 | J27: =IF(AND(D27="Sim",F27="Sim",E27<$C$4),"Não atende","")
A28: 19 | B28: =Matching!C23 -> Esforço físico | C28: =Matching!J23 -> 2 | D28: Sim | E28: 0.5 | F28: Não | G28: =IF(D28="Sim",C28*E28,0) -> 1 | H28: =IF(D28="Sim",C28,0) -> 2 | I28: =IF(D28="Sim",C28*(1-E28),0)+ROW()/1000000 -> 1.000028 | J28: =IF(AND(D28="Sim",F28="Sim",E28<$C$4),"Não atende","")
A29: 20 | B29: =Matching!C24 -> Crescimento | C29: =Matching!J24 -> 2 | D29: Sim | E29: 0.5 | F29: Não | G29: =IF(D29="Sim",C29*E29,0) -> 1 | H29: =IF(D29="Sim",C29,0) -> 2 | I29: =IF(D29="Sim",C29*(1-E29),0)+ROW()/1000000 -> 1.000029 | J29: =IF(AND(D29="Sim",F29="Sim",E29<$C$4),"Não atende","")

Sheet Geografia
A1: Geografia: casa, trabalho e local de estudo
A2: Distância em linha reta, corrigida por um fator de rua, mais a espera do meio de transporte. É estimativa; depois trocamos por rota de verdade.
A4: Meio de deslocamento | B4: Velocidade média (km/h) | C4: Espera e preparo (min)
A5: A pé | B5: 4.5 | C5: 0
A6: Bicicleta | B6: 12 | C6: 2
A7: Moto | B7: 25 | C7: 3
A8: Ônibus | B8: 15 | C8: 12
A9: Carro | B9: 22 | C9: 5
A11: Fator de rota (a rua não é linha reta) | B11: 1.3
A12: Tempo máximo que a pessoa aceita (min) | B12: 45
A13: Meio escolhido | B13: Ônibus
A14: O curso é | B14: Presencial
A15: Tempo máximo até o local de estudo (min) | B15: 30
A17: Ponto (coordenadas de exemplo) | B17: Latitude | C17: Longitude
A18: Casa (bairro, arredondado) | B18: -3.78 | C18: -38.5
A19: Trabalho | B19: -3.73 | C19: -38.52
A20: Local de estudo | B20: -3.75 | C20: -38.53
A22: Trecho | B22: Distância em linha reta (km) | C22: Tempo no meio escolhido (min) | D22: Nota (0 a 1)
A23: Casa → Trabalho | B23: =ROUND(2*6371*ASIN(SQRT(SIN(RADIANS(B19-B18)/2)^2+COS(RADIANS(B18))*COS(RADIANS(B19))*SIN(RADIANS(C19-C18)/2)^2)),1) -> 6 | C23: =ROUND(B23*$B$11/INDEX($B$5:$B$9,MATCH($B$13,$A$5:$A$9,0))*60+INDEX($C$5:$C$9,MATCH($B$13,$A$5:$A$9,0)),0) -> 43 | D23: =IF(C23<=$B$12,1,IF(C23<=1.2*$B$12,0.5,0)) -> 1
A24: Casa → Local de estudo | B24: =ROUND(2*6371*ASIN(SQRT(SIN(RADIANS(B20-B18)/2)^2+COS(RADIANS(B18))*COS(RADIANS(B20))*SIN(RADIANS(C20-C18)/2)^2)),1) -> 4.7 | C24: =ROUND(B24*$B$11/INDEX($B$5:$B$9,MATCH($B$13,$A$5:$A$9,0))*60+INDEX($C$5:$C$9,MATCH($B$13,$A$5:$A$9,0)),0) -> 36
A25: Local de estudo → Trabalho | B25: =ROUND(2*6371*ASIN(SQRT(SIN(RADIANS(B19-B20)/2)^2+COS(RADIANS(B20))*COS(RADIANS(B19))*SIN(RADIANS(C19-C20)/2)^2)),1) -> 2.5 | C25: =ROUND(B25*$B$11/INDEX($B$5:$B$9,MATCH($B$13,$A$5:$A$9,0))*60+INDEX($C$5:$C$9,MATCH($B$13,$A$5:$A$9,0)),0) -> 25
A26: Nota do estudo (curso perto de casa ou do trabalho) | D26: =IF($B$14="EAD",1,IF(MIN(C24,C25)<=$B$15,1,IF(MIN(C24,C25)<=1.5*$B$15,0.5,0))) -> 1
A28: Casa → Trabalho em cada meio | B28: Tempo (min)
A29: =A5 -> A pé | B29: =ROUND($B$23*$B$11/INDEX($B$5:$B$9,MATCH(A5,$A$5:$A$9,0))*60+INDEX($C$5:$C$9,MATCH(A5,$A$5:$A$9,0)),0) -> 104
A30: =A6 -> Bicicleta | B30: =ROUND($B$23*$B$11/INDEX($B$5:$B$9,MATCH(A6,$A$5:$A$9,0))*60+INDEX($C$5:$C$9,MATCH(A6,$A$5:$A$9,0)),0) -> 41
A31: =A7 -> Moto | B31: =ROUND($B$23*$B$11/INDEX($B$5:$B$9,MATCH(A7,$A$5:$A$9,0))*60+INDEX($C$5:$C$9,MATCH(A7,$A$5:$A$9,0)),0) -> 22
A32: =A8 -> Ônibus | B32: =ROUND($B$23*$B$11/INDEX($B$5:$B$9,MATCH(A8,$A$5:$A$9,0))*60+INDEX($C$5:$C$9,MATCH(A8,$A$5:$A$9,0)),0) -> 43
A33: =A9 -> Carro | B33: =ROUND($B$23*$B$11/INDEX($B$5:$B$9,MATCH(A9,$A$5:$A$9,0))*60+INDEX($C$5:$C$9,MATCH(A9,$A$5:$A$9,0)),0) -> 26
A35: A nota casa → trabalho alimenta o par 1 do Matching; a nota do estudo alimenta o par 7. Se o curso é EAD, a nota do estudo é 1: não importa onde a pessoa mora.
A36: Privacidade: guardamos a coordenada arredondada (cerca de 500 m), nunca o endereço exato, até a pessoa aceitar mostrar à empresa.
A37: As coordenadas acima são só um exemplo (Fortaleza, aproximadas). Velocidades e esperas são premissas nossas, a calibrar com dados reais.
A38: Para virar o CEP em coordenada o app precisa de um serviço de endereços; é a mesma peça que a entrega por CEP do Vem Comer vai usar.

Sheet Cadastro
A1: Telas de entrada: tudo de tocar
A2: Candidato, funcionário e empresa entram pelo mesmo caminho. A coluna 'Base legal' diz por que cada dado é pedido.
A4: Ordem | B4: Tela | C4: O que a pessoa vê | D4: Como responde | E4: Opções | F4: Obrigatório? | G4: Para quê | H4: Base legal (confirmar com advogado) | I4: Vai para a empresa?
A5: 1 | B5: Entrar | C5: Qual o seu celular? | D5: Digitar o número (ou falar). Código por mensagem. | E5: - | F5: Sim | G5: Criar a conta e avisar de vaga. | H5: Execução do serviço | I5: Não
A6: 2 | B6: Quem é você | C6: O que você quer agora? | D6: Um toque | E6: Procuro emprego; Quero estágio ou jovem aprendiz; Já trabalho e quero crescer; Sou autônomo ou MEI; Sou empresa | F6: Sim | G6: Abrir o caminho certo (candidato, funcionário ou empresa). | H6: Execução do serviço | I6: Não
A7: 3 | B7: Onde você está | C7: Onde você mora? | D7: Um toque em 'usar onde estou' ou digitar o CEP | E7: Guardamos só a região do bairro (arredondada) | F7: Sim | G7: Calcular tempo de deslocamento até vagas e cursos. | H7: Execução do serviço; compartilha só com consentimento | I7: Só a região, se a pessoa aceitar
A8: 4 | B8: Seu trabalho | C8: Que trabalho você procura? | D8: Voz ou lista (até 3 ocupações) | E8: Lista de ocupações por área | F8: Sim | G8: Match por função. | H8: Execução do serviço | I8: Sim
A9: 5 | B9: Seu trabalho | C9: Quanto tempo de experiência você tem? | D9: Um toque | E9: Nenhuma; até 1 ano; 1 a 3; 3 a 5; mais de 5 | F9: Sim | G9: Match por experiência. | H9: Execução do serviço | I9: Sim
A10: 6 | B10: Estudo | C10: Até onde você estudou? | D10: Um toque | E10: Fundamental; médio; técnico; superior; pós (completo ou cursando) | F10: Sim | G10: Match por escolaridade e sugestão de curso. | H10: Execução do serviço | I10: Sim
A11: 7 | B11: Horário | C11: Quando você pode trabalhar? | D11: Toques (pode marcar vários) | E11: Manhã; tarde; noite; madrugada; fins de semana; escala 12x36 | F11: Sim | G11: Match por turno. | H11: Execução do serviço | I11: Sim
A12: 8 | B12: Contrato | C12: Que tipo de vaga você aceita? | D12: Toques (pode marcar vários) | E12: CLT; estágio; jovem aprendiz; temporário; diária; MEI ou PJ | F12: Sim | G12: Match por contrato. | H12: Execução do serviço | I12: Sim
A13: 9 | B13: Currículo | C13: Quer montar seu currículo falando? | D13: Voz, foto de um currículo antigo ou preencher por toque | E13: Gerar currículo básico | F13: Não | G13: Criar o currículo sem digitar. O básico fica gratuito? (decisão pendente do GD). | H13: Execução do serviço | I13: Só se a pessoa publicar
A14: 10 | B14: Cursos | C14: Quer ver cursos para melhorar sua nota nas vagas? | D14: Um toque | E14: Sim; depois | F14: Não | G14: Recomendar cursos (nossos ou de parceiros). | H14: Execução do serviço | I14: Não
A15: 11 | B15: Avisos | C15: Posso avisar você de vagas e cursos por mensagem? | D15: Caixa desmarcada: a pessoa precisa tocar | E15: Sim; não | F15: Não | G15: Mensagens de marketing do próprio serviço. | H15: Consentimento (separado, pode ser revogado a qualquer hora) | I15: Não
A16: 12 | B16: Pesquisa | C16: Posso usar suas respostas, sem mostrar seu nome, em estudos do mercado de trabalho? | D16: Caixa desmarcada | E16: Sim; não | F16: Não | G16: Base de dados e marketing durante a semana de teste. | H16: Consentimento (separado, pode ser revogado a qualquer hora) | I16: Não (dados anônimos)
... A19: 15 | B19: Empresa | C19: Quantas vagas pretende anunciar por mês? | D19: Um toque | E19: 0 a 10; 11 a 500; 501 a 1.000; mais de 1.000 | F19: Sim | G19: Mostrar o plano certo antes de cobrar. | H19: Execução do contrato | I19: -
A21: Não pedimos: raça ou cor, religião, estado civil, filhos, gravidez, idade como filtro, foto obrigatória, orientação sexual, opinião política, saúde. Esses dados não entram no matching. (Lei 9.029/1995 e LGPD; conferir com advogado.)

Sheet Entrevista do currículo
A1: Entrevista do currículo: a pessoa tira uma foto ou fala, e o sistema pergunta o que falta
A2: Tudo de toque ou voz. O sistema só escreve o que a pessoa disse, e ela confirma cada trecho. Na semana de teste o currículo aparece na tela, sem baixar.
A4: Nº | B4: Etapa | C4: O que a pessoa vê | D4: Como responde | E4: Opções de toque | F4: Se não souber ou não tiver | G4: O que entra no currículo | H4: Liga com
A5: 1 | B5: Começar | C5: Como você quer fazer seu currículo? | D5: Um toque | E5: Tirar foto de um currículo que eu já tenho; Falar; Preencher tocando | F5: Qualquer caminho serve; dá para mudar depois. | G5: - | H5: -
A6: 2 | B6: Foto | C6: Tire uma foto do seu currículo, ou de um papel com seus dados. | D6: Câmera ou galeria, várias páginas | E6: Câmera; Galeria | F6: Foto ruim: o sistema pede 'mais luz, de novo'. | G6: O sistema lê e monta um rascunho. Marca com '?' o que não entendeu. | H6: -
A7: 3 | B7: Conferir | C7: Está certo? Toque no que precisa mudar. | D7: Toque ou voz ('troque a empresa para Padaria Sol') | E7: Está certo; Mudar | F7: Pode corrigir por voz quantas vezes quiser. | G7: O rascunho corrigido. | H7: -
A8: 4 | B8: Nome | C8: Como você quer aparecer no currículo? | D8: Confirma o nome do cadastro | E8: Esse nome; Outro nome | F8: - | G8: Cabeçalho com nome e contato. | H8: Cadastro
A9: 5 | B9: Objetivo | C9: Que trabalho você procura? | D9: Voz ou lista de ocupações | E9: Lista de ocupações por área | F9: 'Ainda não sei': mostra o teste de interesses. | G9: Uma linha de objetivo. | H9: Teste de interesses; match: função
A10: 6 | B10: Experiências | C10: Você já trabalhou? Vale bico, trabalho informal, ajudar a família, estágio e voluntário. | D10: Um toque | E10: Já trabalhei; Só bicos e ajuda em casa; Nunca trabalhei | F10: 'Nunca trabalhei': vai para 'Buscar na vida' (etapas 19 a 30). | G10: - | H10: -
A11: 7 | B11: Experiência: lugar | C11: Onde você trabalhou? | D11: Voz ou toque | E11: Nome do lugar; Por conta própria; Ajudei a família; Voluntário; Estágio | F11: Não lembra o nome: 'um lugar de [área]'. | G11: Nome do lugar e tipo de vínculo. | H11: -
A12: 8 | B12: Experiência: função | C12: Como chamavam o seu serviço? | D12: Voz ou lista por área | E12: Cargos comuns da área (aba Tarefas por área) | F12: 'Não tinha nome': pergunta o que fazia. | G12: Cargo. Cargo de profissão regulada só entra com o registro. | H12: Match: função
A13: 9 | B13: Experiência: início | C13: Quando você começou? | D13: Toque em mês e ano | E13: Seletor de mês e ano | F13: 'Não lembro': 'foi há quantos anos?' | G13: Data aproximada. | H13: Match: experiência
A14: 10 | B14: Experiência: fim | C14: Quando você saiu? | D14: Toque em mês e ano | E14: Seletor; Ainda trabalho aqui | F14: Mesmo caminho do início. | G14: Período e tempo total. | H14: Match: experiência
A15: 11 | B15: Experiência: dia a dia | C15: O que você fazia no dia a dia? | D15: Marcar tarefas e falar livre | E15: Tarefas da área (aba Tarefas por área) | F15: 'Não sei dizer': o sistema mostra exemplos para tocar. | G15: De 3 a 5 frases curtas, com o verbo no passado. | H15: Match: habilidades
A16: 12 | B16: Experiência: ferramentas | C16: Que máquinas, programas ou ferramentas você usava? | D16: Marcar | E16: Ferramentas da área | F16: 'Nenhuma'. | G16: Uma linha de ferramentas. | H16: Match: ferramentas
... A42: 38 | B42: Próximo passo | C42: Para ter mais chances, faça este curso (depois de tudo pronto, no máximo 3 sugestões, com o motivo). | D42: Toque | E42: Fazer agora; Ver depois | F42: Curso livre nosso vem primeiro; curso de parceiro leva a etiqueta. | G42: - | H42: Aba Ideias de cursos e Parcerias
A44: Regras da entrevista
B45: O sistema só escreve o que a pessoa disse. Datas, empresas e números nunca são inventados ou 'melhorados'.
B46: Tudo que a pessoa falar aparece escrito para ela confirmar antes de entrar no currículo. O áudio é apagado depois de virar texto.
B47: Não pergunta idade, estado civil, filhos, foto, saúde, religião nem cor. Foto da pessoa só se ela quiser, e nunca criada por IA.
B48: Tempo parado entre empregos não é cobrado nem destacado. O motivo da saída fica só com a pessoa.
B49: Trabalho informal, bico, ajuda em negócio da família e voluntariado valem como experiência.
B50: Cargo de profissão regulada (por exemplo, enfermagem) só aparece se a pessoa tiver o registro. O sistema avisa em vez de escrever.
B51: A pessoa pode parar e voltar: o que respondeu fica salvo.
B52: O curso oferecido no fim vem do que a pessoa disse. Primeiro o curso livre nosso; o de parceiro leva a etiqueta 'Parceiro'.

Sheet Tarefas por área
A1: Tarefas, ferramentas e habilidades por área (as bolinhas de tocar)
A2: A pessoa toca no que fazia, em vez de digitar. O sistema usa as mesmas listas no currículo e no match.
A4: Área | B4: Cargos comuns | C4: Tarefas do dia a dia | D4: Ferramentas | E4: Habilidades | F4: Cursos que combinam
A5: Administrativa | B5: Auxiliar administrativo; Recepcionista; Assistente financeiro; Secretário ou secretária; Auxiliar de escritório | C5: Atender telefone e e-mail; Organizar documentos e arquivos; Lançar notas e contas; Controlar agenda; Preparar planilhas e relatórios; Receber visitas; Fazer pedidos de material; Conferir pagamentos | D5: Excel; Word; WhatsApp comercial; Sistema de gestão; E-mail | E5: Organização; Atenção a detalhes; Escrita; Responsabilidade | F5: Excel do zero; Informática básica no celular e no computador; Comunicação e escrita profissional; Recepcionista
A6: Mecânica de carro e moto | B6: Ajudante de mecânico; Mecânico; Auxiliar de oficina; Borracheiro; Eletricista automotivo | C6: Trocar óleo e filtros; Fazer revisão; Trocar pastilhas e freios; Diagnosticar barulho ou falha; Atender o cliente e explicar o serviço; Fazer orçamento; Limpar e organizar a oficina; Usar scanner | D6: Chaves e ferramentas manuais; Elevador; Scanner; Multímetro | E6: Diagnóstico; Cuidado com segurança; Atendimento; Organização | F6: Mecânica de motos (escola parceira); Mecânica automotiva básica (parceiro); Atendimento de balcão
A7: Logística e estoque | B7: Auxiliar de estoque; Conferente; Separador de pedidos; Estoquista; Auxiliar de expedição | C7: Receber e conferir mercadoria; Separar pedidos; Organizar o estoque; Fazer inventário; Carregar e descarregar; Emitir etiquetas; Controlar entrada e saída | D7: Coletor de dados; Paleteira; Empilhadeira (com habilitação); Sistema de estoque; Planilha | E7: Atenção; Organização; Pontualidade; Resistência | F7: Logística e estoque; Conferência e separação de pedidos; Almoxarifado; Operador de empilhadeira (parceiro)
A8: Vendas e comércio | B8: Vendedor; Balconista; Promotor de vendas; Repositor; Vendedor externo | C8: Atender e oferecer produtos; Montar vitrine e repor mercadoria; Fazer orçamento; Fechar venda; Fazer pós-venda pelo WhatsApp; Bater meta; Procurar novos clientes; Responder redes sociais | D8: Maquininha; Sistema de vendas; WhatsApp comercial; Instagram; Canva | E8: Comunicação; Persuasão; Paciência; Organização | F8: Vendas para quem está começando; Vender pelas redes sociais; Atendimento ao cliente por WhatsApp
A9: Atendimento e caixa | B9: Atendente; Operador de caixa; Recepcionista; Atendente de telemarketing; Frentista | C9: Receber e atender o cliente; Operar o caixa e dar troco; Resolver reclamação; Atender telefone; Fechar o caixa; Cadastrar clientes; Orientar sobre produtos; Atender pelo WhatsApp | D9: Sistema de caixa; Maquininha; Telefone; WhatsApp | E9: Educação; Calma; Matemática básica; Agilidade | F9: Atendimento de balcão; Operador de caixa; Como lidar com cliente difícil
A10: Cozinha e salão | B10: Auxiliar de cozinha; Cozinheiro; Garçom; Copeiro; Pizzaiolo; Barista; Atendente de lanchonete; Padeiro | C10: Preparar ingredientes; Cozinhar pratos; Montar pratos e marmitas; Servir mesas; Anotar pedidos; Limpar e higienizar; Receber e guardar mercadoria; Atender delivery | D10: Fogão e forno; Chapa; Comanda e sistema; Maquininha | E10: Higiene; Rapidez; Trabalho em equipe; Organização | F10: Garçom e atendimento no salão; Boas práticas de manipulação de alimentos; Auxiliar de cozinha (parceiro); Montagem e entrega de marmita e delivery
A11: Construção e reparos | B11: Ajudante de pedreiro; Pedreiro; Pintor; Eletricista; Encanador; Servente | C11: Preparar massa e material; Assentar tijolo e piso; Pintar paredes; Fazer instalações elétricas; Fazer instalações hidráulicas; Medir e fazer orçamento; Limpar a obra; Seguir regras de segurança | D11: Colher e nível; Furadeira; Multímetro; Trena; Equipamento de proteção | E11: Força; Atenção; Segurança; Medidas | F11: Segurança em obra: noções (não substitui NR); Orçamento de pequenas obras; Pintura de parede; Instalação hidráulica básica; Eletricista predial (parceiro)
A12: Campo e agro | B12: Trabalhador rural; Tratorista; Ordenhador; Auxiliar de granja; Caseiro | C12: Plantar e colher; Cuidar de animais; Ordenhar; Operar trator; Irrigar; Aplicar insumos com segurança; Vender a produção; Cuidar de cerca e instalações | D12: Trator; Ferramentas agrícolas; Irrigação; Celular para vendas | E12: Resistência; Observação; Responsabilidade | F12: Boas práticas no campo; Gestão da propriedade rural; Vendas diretas do produtor (feira e WhatsApp); Operador de máquinas agrícolas (parceiro)
A13: Cuidados e saúde | B13: Cuidador; Recepcionista de clínica; Babá; Auxiliar de saúde (profissão regulada: só com registro) | C13: Acompanhar a rotina; Dar medicamento conforme a receita; Ajudar na higiene e no conforto; Atender e agendar pacientes; Organizar fichas; Preparar o ambiente; Aplicar primeiros socorros; Conversar com a família | D13: Termômetro; Aparelho de pressão; Sistema de agenda | E13: Paciência; Empatia; Atenção | F13: Cuidador de idosos (parceiro); Primeiros socorros no trabalho; Recepção em clínicas; Técnico de enfermagem (escola parceira)
A14: Beleza e estética | B14: Cabeleireiro; Manicure; Barbeiro; Recepcionista de salão; Maquiador | C14: Cortar cabelo; Fazer unhas; Atender e agendar clientes; Higienizar ferramentas; Vender produtos; Divulgar no Instagram; Controlar o caixa; Montar combos de serviço | D14: Tesoura e máquina; Secador; Agenda; Instagram | E14: Cuidado; Criatividade; Atendimento | F14: Atendimento em salão de beleza; Instagram para negócios; Preço de venda e lucro
A15: Tecnologia e escritório digital | B15: Suporte técnico; Assistente de TI; Designer júnior; Social media; Editor de vídeo | C15: Instalar e configurar computadores; Atender chamados; Criar artes no Canva; Postar e responder redes; Editar vídeos; Montar planilhas; Cuidar de segurança e senhas; Montar sites simples | D15: Windows; Canva; Excel; Editor de vídeo no celular; WhatsApp Business | E15: Lógica; Curiosidade; Comunicação | F15: Suporte técnico em informática; Canva para quem nunca usou; Edição de vídeo no celular; Criação de site simples; Lógica de programação para iniciantes
... A17: Motorista e entregas | B17: Motorista; Entregador de moto; Motorista de aplicativo; Motoboy | C17: Entregar pedidos no prazo; Planejar rotas; Conferir a carga; Atender o cliente na entrega; Cuidar do veículo; Cumprir as regras de trânsito; Registrar entregas; Receber pagamento na entrega | D17: Moto; Carro; Aplicativo de rota; Maquininha | E17: Direção segura; Pontualidade; Atendimento | F17: Entregador de moto e bicicleta: rotina e segurança; Direção defensiva (não substitui curso exigido por lei); Motorista de aplicativo: atendimento e segurança
A19: Os nomes dos cursos são os da aba Ideias de cursos e Cursos com parceiros. Cargo de profissão regulada só entra no currículo com o registro.

Sheet Currículos
A1: Modelos de currículo e cores
A2: 26 modelos x 9 paletas. Letra: as do app (Bricolage Grotesque para títulos, Instrument Sans para texto). Leitura automática (ATS) é avaliação nossa.
A3: Modelos | B3: =COUNTA(B7:B32) -> 26 | C3: Cores | D3: =COUNTA(B35:B43) -> 9 | E3: Combinações | F3: =B3*D3 -> 234
A6: Nº | B6: Modelo | C6: Estilo | D6: Colunas | E6: Foto | F6: Páginas | G6: Para quem | H6: Destaque | I6: Leitura automática (ATS) | J6: Letra
A7: 1 | B7: Claro | C7: Minimalista, nome centralizado | D7: 1 | E7: Sem foto | F7: 1 | G7: Qualquer pessoa | H7: Equilíbrio entre experiência e formação | I7: Alta | J7: Bricolage Grotesque + Instrument Sans
A8: 2 | B8: Direto | C8: Nome à esquerda com linha de cor | D8: 1 | E8: Sem foto | F8: 1 | G8: Qualquer pessoa | H8: Experiência primeiro | I8: Alta | J8: Bricolage Grotesque + Instrument Sans
A9: 3 | B9: Faixa lateral | C9: Coluna lateral com contatos e habilidades | D9: 2 | E9: Foto opcional | F9: 1 | G9: Atendimento, vendas, administrativo | H9: Habilidades à vista | I9: Média | J9: Bricolage Grotesque + Instrument Sans
A10: 4 | B10: Linha do tempo | C10: Linha vertical com as experiências | D10: 1 | E10: Sem foto | F10: 1 | G10: Quem tem várias experiências | H10: Trajetória | I10: Média | J10: Bricolage Grotesque + Instrument Sans
A11: 5 | B11: Primeiro emprego | C11: Objetivo, cursos e habilidades no topo | D11: 1 | E11: Sem foto | F11: 1 | G11: Quem nunca trabalhou com carteira | H11: Cursos, projetos, trabalho voluntário e informal | I11: Alta | J11: Bricolage Grotesque + Instrument Sans
A12: 6 | B12: Operacional | C12: Disponibilidade e certificados em destaque | D12: 1 | E12: Sem foto | F12: 1 | G12: Fábrica, armazém, obra, produção | H12: NR, CNH, cursos práticos | I12: Alta | J12: Bricolage Grotesque + Instrument Sans
A13: 7 | B13: Técnico | C13: Ferramentas e certificações em quadro | D13: 1 | E13: Sem foto | F13: 1 | G13: Eletricista, mecânico, técnico | H13: Equipamentos e certificações | I13: Alta | J13: Bricolage Grotesque + Instrument Sans
A14: 8 | B14: Atendimento e vendas | C14: Resultados e idiomas em destaque | D14: 1 | E14: Foto opcional | F14: 1 | G14: Balcão, caixa, vendas | H14: Metas batidas, idiomas | I14: Alta | J14: Bricolage Grotesque + Instrument Sans
A15: 9 | B15: Saúde | C15: Registro profissional e plantões | D15: 1 | E15: Sem foto | F15: 1 | G15: Enfermagem, farmácia, clínicas | H15: Registro no conselho, especialidades | I15: Alta | J15: Bricolage Grotesque + Instrument Sans
A16: 10 | B16: Cozinha e salão | C16: Praças, turnos e boas práticas | D16: 1 | E16: Sem foto | F16: 1 | G16: Gastronomia e hotelaria | H16: Praças, manipulação de alimentos | I16: Alta | J16: Bricolage Grotesque + Instrument Sans
A17: 11 | B17: Campo e agro | C17: Máquinas, cultivos e cursos | D17: 1 | E17: Sem foto | F17: 1 | G17: Agro e pecuária | H17: Máquinas, cadeias, cursos | I17: Alta | J17: Bricolage Grotesque + Instrument Sans
A18: 12 | B18: Motorista e entregador | C18: CNH, veículos e rotas | D18: 1 | E18: Sem foto | F18: 1 | G18: Motoristas, entregadores | H18: Categoria da CNH, tipos de veículo | I18: Alta | J18: Bricolage Grotesque + Instrument Sans
... A32: 26 | B32: Letra grande | C32: Letra maior e contraste alto | D32: 1 | E32: Sem foto | F32: 2 | G32: Quem tem baixa visão ou lê no celular | H32: Leitura fácil | I32: Alta | J32: Instrument Sans, tamanho 20% maior
A34: Nº | B34: Cor | C34: Principal | D34: Escura | E34: Clara | F34: Destaque | G34: Escura sobre a clara (contraste) | H34: Principal sobre branco (contraste) | I34: Texto na cor principal? | J34: Observação
A35: 1 | B35: Vermelho | C35: #B42318 | D35: #7F1D14 | E35: #FDECEA | F35: #FFC83A | G35: 8.8 | H35: 6.6 | I35: Sim | J35: Texto sempre em cor escura sobre fundo claro (contraste de 4,5 ou mais).
A36: 2 | B36: Laranja | C36: #C2410C | D36: #8A2E08 | E36: #FFF1E6 | F36: - | G36: 7.7 | H36: 5.2 | I36: Sim | J36: Texto sempre em cor escura sobre fundo claro (contraste de 4,5 ou mais).
A37: 3 | B37: Amarelo | C37: #FFC83A | D37: #5C4200 | E37: #FFF6D6 | F37: #B42318 | G37: 8.7 | H37: 1.5 | I37: Não: usar só em faixas e detalhes | J37: Texto sempre em cor escura sobre fundo claro (contraste de 4,5 ou mais).
A38: 4 | B38: Verde | C38: #1E6B3C | D38: #123B2B | E38: #E6F4EA | F38: - | G38: 11 | H38: 6.5 | I38: Sim | J38: Texto sempre em cor escura sobre fundo claro (contraste de 4,5 ou mais).
A39: 5 | B39: Azul | C39: #1D4ED8 | D39: #1E3A8A | E39: #E8EEFF | F39: - | G39: 8.9 | H39: 6.7 | I39: Sim | J39: Texto sempre em cor escura sobre fundo claro (contraste de 4,5 ou mais).
A40: 6 | B40: Roxo | C40: #6D28D9 | D40: #4C1D95 | E40: #F1E9FE | F40: - | G40: 9.3 | H40: 7.1 | I40: Sim | J40: Texto sempre em cor escura sobre fundo claro (contraste de 4,5 ou mais).
A41: 7 | B41: Marrom | C41: #7C4A24 | D41: #4A2A12 | E41: #F7EDE3 | F41: - | G41: 11.1 | H41: 7.3 | I41: Sim | J41: Texto sempre em cor escura sobre fundo claro (contraste de 4,5 ou mais).
A42: 8 | B42: Rosa | C42: #BE185D | D42: #831843 | E42: #FDE7F0 | F42: - | G42: 8.2 | H42: 6 | I42: Sim | J42: Texto sempre em cor escura sobre fundo claro (contraste de 4,5 ou mais).
A43: 9 | B43: Grafite | C43: #1F2937 | D43: #111827 | E43: #EEF0F3 | F43: - | G43: 15.5 | H43: 14.7 | I43: Sim | J43: Texto sempre em cor escura sobre fundo claro (contraste de 4,5 ou mais).
B44: Mesmas cores das logomarcas do Vem Comer. Contraste calculado pela fórmula WCAG (luminância relativa); 4,5 ou mais é o mínimo para texto normal.

Sheet Perfil
A1: Jeito de ser: 25 frases (Big Five do IPIP)
A2: Itens do IPIP, de domínio público: podem ser copiados, traduzidos e usados para qualquer fim (ipip.ori.org). A tradução é nossa e precisa de revisão de psicólogo.
A3: Resposta: 1 discordo muito, 2 discordo, 3 nem um nem outro, 4 concordo, 5 concordo muito. Exemplo: 4. Na tela vira 5 botões; ninguém digita.
A6: Nº | B6: Fator | C6: Frase | D6: Sentido | E6: Resposta (1 a 5) | F6: Pontos | G6: Item original (IPIP) | I6: Fator | J6: Média (1 a 5)
A7: 1 | B7: Extroversão | C7: Sou a alma da festa. | D7: Normal | F7: =IF(E7="","",IF(D7="Invertido",6-E7,E7)) | G7: Am the life of the party. | I7: Extroversão | J7: =IFERROR(AVERAGEIF($B$7:$B$31,I7,$F$7:$F$31),"")
A8: 2 | B8: Extroversão | C8: Sinto-me à vontade perto das pessoas. | D8: Normal | F8: =IF(E8="","",IF(D8="Invertido",6-E8,E8)) | G8: Feel comfortable around people. | I8: Amabilidade | J8: =IFERROR(AVERAGEIF($B$7:$B$31,I8,$F$7:$F$31),"")
A9: 3 | B9: Extroversão | C9: Falo pouco. | D9: Invertido | F9: =IF(E9="","",IF(D9="Invertido",6-E9,E9)) | G9: Don't talk a lot. | I9: Responsabilidade | J9: =IFERROR(AVERAGEIF($B$7:$B$31,I9,$F$7:$F$31),"")
A10: 4 | B10: Extroversão | C10: Fico em segundo plano. | D10: Invertido | F10: =IF(E10="","",IF(D10="Invertido",6-E10,E10)) | G10: Keep in the background. | I10: Calma | J10: =IFERROR(AVERAGEIF($B$7:$B$31,I10,$F$7:$F$31),"")
A11: 5 | B11: Extroversão | C11: Puxo conversa. | D11: Normal | F11: =IF(E11="","",IF(D11="Invertido",6-E11,E11)) | G11: Start conversations. | I11: Curiosidade | J11: =IFERROR(AVERAGEIF($B$7:$B$31,I11,$F$7:$F$31),"")
A12: 6 | B12: Amabilidade | C12: Interesso-me pelas pessoas. | D12: Normal | F12: =IF(E12="","",IF(D12="Invertido",6-E12,E12)) | G12: Am interested in people.
A13: 7 | B13: Amabilidade | C13: Tenho o coração mole. | D13: Normal | F13: =IF(E13="","",IF(D13="Invertido",6-E13,E13)) | G13: Have a soft heart. | I13: Média alta (4 a 5), média (3), baixa (1 a 2). Não é nota boa ou ruim: é jeito de ser.
A14: 8 | B14: Amabilidade | C14: Não me interesso pelos problemas dos outros. | D14: Invertido | F14: =IF(E14="","",IF(D14="Invertido",6-E14,E14)) | G14: Am not interested in other people's problems. | I14: O fator Calma é o mais sensível: só para a pessoa, nunca aparece para a empresa.
A15: 9 | B15: Amabilidade | C15: Reservo tempo para os outros. | D15: Normal | F15: =IF(E15="","",IF(D15="Invertido",6-E15,E15)) | G15: Take time out for others.
A16: 10 | B16: Amabilidade | C16: Sinto pouca preocupação com os outros. | D16: Invertido | F16: =IF(E16="","",IF(D16="Invertido",6-E16,E16)) | G16: Feel little concern for others.
A17: 11 | B17: Responsabilidade | C17: Estou sempre preparado. | D17: Normal | F17: =IF(E17="","",IF(D17="Invertido",6-E17,E17)) | G17: Am always prepared.
A18: 12 | B18: Responsabilidade | C18: Presto atenção aos detalhes. | D18: Normal | F18: =IF(E18="","",IF(D18="Invertido",6-E18,E18)) | G18: Pay attention to details.
A19: 13 | B19: Responsabilidade | C19: Resolvo as tarefas logo. | D19: Normal | F19: =IF(E19="","",IF(D19="Invertido",6-E19,E19)) | G19: Get chores done right away.
A20: 14 | B20: Responsabilidade | C20: Sigo um horário. | D20: Normal | F20: =IF(E20="","",IF(D20="Invertido",6-E20,E20)) | G20: Follow a schedule.
A21: 15 | B21: Responsabilidade | C21: Deixo meus deveres de lado. | D21: Invertido | F21: =IF(E21="","",IF(D21="Invertido",6-E21,E21)) | G21: Neglect my duties.
A22: 16 | B22: Calma | C22: Fico tranquilo na maior parte do tempo. | D22: Normal | F22: =IF(E22="","",IF(D22="Invertido",6-E22,E22)) | G22: Am relaxed most of the time.
A23: 17 | B23: Calma | C23: Estresso-me com facilidade. | D23: Invertido | F23: =IF(E23="","",IF(D23="Invertido",6-E23,E23)) | G23: Get stressed out easily.
A24: 18 | B24: Calma | C24: Preocupo-me com as coisas. | D24: Invertido | F24: =IF(E24="","",IF(D24="Invertido",6-E24,E24)) | G24: Worry about things.
A25: 19 | B25: Calma | C25: Raramente me irrito. | D25: Normal | F25: =IF(E25="","",IF(D25="Invertido",6-E25,E25)) | G25: Rarely get irritated.
A26: 20 | B26: Calma | C26: Meu humor muda muito. | D26: Invertido | F26: =IF(E26="","",IF(D26="Invertido",6-E26,E26)) | G26: Change my mood a lot.
... A31: 25 | B31: Curiosidade | C31: Tenho vocabulário rico. | D31: Normal | F31: =IF(E31="","",IF(D31="Invertido",6-E31,E31)) | G31: Have a rich vocabulary.

Sheet Interesses
A1: Interesses de carreira: 18 frases (modelo RIASEC)
A2: O modelo RIASEC (Holland) é a base do Interest Profiler do O*NET (Creative Commons 4.0, crédito ao Departamento do Trabalho dos EUA). As frases daqui são nossas.
A3: Resposta: 1 não curto, 2 tanto faz, 3 curto. Exemplo: 3. Na tela vira carinha triste, neutra e feliz.
A6: Nº | B6: Tipo | C6: Frase | D6: Resposta (1 a 3) | F6: Tipo | G6: Soma | H6: Combina com
A7: 1 | B7: Realista (fazer com as mãos) | C7: Consertar uma máquina, uma moto ou um aparelho. | F7: Realista (fazer com as mãos) | G7: =SUMIF($B$7:$B$24,F7,$D$7:$D$24) -> 0 | H7: Indústria, agro, construção, mecânica, logística
A8: 2 | B8: Realista (fazer com as mãos) | C8: Trabalhar ao ar livre, no campo ou numa obra. | F8: Investigativo (entender e descobrir) | G8: =SUMIF($B$7:$B$24,F8,$D$7:$D$24) -> 0 | H8: Tecnologia, saúde, qualidade, laboratório, dados
A9: 3 | B9: Realista (fazer com as mãos) | C9: Montar, instalar ou operar equipamentos. | F9: Artístico (criar) | G9: =SUMIF($B$7:$B$24,F9,$D$7:$D$24) -> 0 | H9: Moda, design, gastronomia, comunicação, eventos
A10: 4 | B10: Investigativo (entender e descobrir) | C10: Descobrir por que uma coisa deu errado. | F10: Social (ajudar e ensinar) | G10: =SUMIF($B$7:$B$24,F10,$D$7:$D$24) -> 0 | H10: Saúde, educação, atendimento, hotelaria, cuidados
A11: 5 | B11: Investigativo (entender e descobrir) | C11: Ler e pesquisar para aprender um assunto a fundo. | F11: Empreendedor (vender e liderar) | G11: =SUMIF($B$7:$B$24,F11,$D$7:$D$24) -> 0 | H11: Vendas, comércio, gerência, MEI e negócio próprio
A12: 6 | B12: Investigativo (entender e descobrir) | C12: Analisar números ou resultados para tirar conclusões. | F12: Convencional (organizar) | G12: =SUMIF($B$7:$B$24,F12,$D$7:$D$24) -> 0 | H12: Administração, finanças, estoque, escritório, recepção
A13: 7 | B13: Artístico (criar) | C13: Desenhar, fotografar, fazer vídeos ou decorar.
A14: 8 | B14: Artístico (criar) | C14: Inventar receitas, roupas, peças ou textos. | F14: Tipo mais forte | G14: =IF(MAX(G7:G12)=0,"",INDEX(F7:F12,MATCH(MAX(G7:G12),G7:G12,0)))
A15: 9 | B15: Artístico (criar) | C15: Montar uma vitrine, um cardápio ou uma página bonita.
A16: 10 | B16: Social (ajudar e ensinar) | C16: Atender e ajudar pessoas com problemas.
A17: 11 | B17: Social (ajudar e ensinar) | C17: Ensinar alguém a fazer uma tarefa.
A18: 12 | B18: Social (ajudar e ensinar) | C18: Cuidar de pessoas: crianças, idosos, pacientes.
A19: 13 | B19: Empreendedor (vender e liderar) | C19: Convencer alguém a comprar ou a topar uma ideia.
A20: 14 | B20: Empreendedor (vender e liderar) | C20: Liderar um grupo para bater uma meta.
A21: 15 | B21: Empreendedor (vender e liderar) | C21: Abrir ou tocar o meu próprio negócio.
A22: 16 | B22: Convencional (organizar) | C22: Organizar documentos, estoque ou agenda.
A23: 17 | B23: Convencional (organizar) | C23: Lançar dados e conferir contas com cuidado.
A24: 18 | B24: Convencional (organizar) | C24: Seguir um passo a passo sempre do mesmo jeito.

Sheet Desempenho
A1: Desempenho do funcionário: 16 frases
A2: Uma versão para o próprio funcionário e outra para o gestor (a frase passa de 'eu' para 'essa pessoa'). Serve para desenvolver, com conversa, e não para decidir demissão sozinha.
A3: Resposta: 1 ainda não, 2 às vezes, 3 quase sempre, 4 sempre. Exemplo: 3. O funcionário sabe que está sendo avaliado e vê o resultado.
A6: Nº | B6: Competência | C6: Frase | D6: Eu (1 a 4) | E6: Gestor (1 a 4) | G6: Competência | H6: Eu | I6: Gestor | J6: Diferença
A7: 1 | B7: Qualidade do trabalho | C7: Entrego o trabalho como combinado. | G7: Qualidade do trabalho | H7: =IFERROR(AVERAGEIF($B$7:$B$22,G7,$D$7:$D$22),"") | I7: =IFERROR(AVERAGEIF($B$7:$B$22,G7,$E$7:$E$22),"") | J7: =IF(OR(H7="",I7=""),"",I7-H7)
A8: 2 | B8: Qualidade do trabalho | C8: Confiro o meu trabalho antes de entregar. | G8: Pontualidade e prazos | H8: =IFERROR(AVERAGEIF($B$7:$B$22,G8,$D$7:$D$22),"") | I8: =IFERROR(AVERAGEIF($B$7:$B$22,G8,$E$7:$E$22),"") | J8: =IF(OR(H8="",I8=""),"",I8-H8)
A9: 3 | B9: Pontualidade e prazos | C9: Chego no horário e aviso quando não puder vir. | G9: Trabalho em equipe | H9: =IFERROR(AVERAGEIF($B$7:$B$22,G9,$D$7:$D$22),"") | I9: =IFERROR(AVERAGEIF($B$7:$B$22,G9,$E$7:$E$22),"") | J9: =IF(OR(H9="",I9=""),"",I9-H9)
A10: 4 | B10: Pontualidade e prazos | C10: Cumpro os prazos que combinei. | G10: Atendimento | H10: =IFERROR(AVERAGEIF($B$7:$B$22,G10,$D$7:$D$22),"") | I10: =IFERROR(AVERAGEIF($B$7:$B$22,G10,$E$7:$E$22),"") | J10: =IF(OR(H10="",I10=""),"",I10-H10)
A11: 5 | B11: Trabalho em equipe | C11: Ajudo os colegas quando precisam. | G11: Iniciativa | H11: =IFERROR(AVERAGEIF($B$7:$B$22,G11,$D$7:$D$22),"") | I11: =IFERROR(AVERAGEIF($B$7:$B$22,G11,$E$7:$E$22),"") | J11: =IF(OR(H11="",I11=""),"",I11-H11)
A12: 6 | B12: Trabalho em equipe | C12: Aceito pedir ajuda e receber orientação. | G12: Segurança e normas | H12: =IFERROR(AVERAGEIF($B$7:$B$22,G12,$D$7:$D$22),"") | I12: =IFERROR(AVERAGEIF($B$7:$B$22,G12,$E$7:$E$22),"") | J12: =IF(OR(H12="",I12=""),"",I12-H12)
A13: 7 | B13: Atendimento | C13: Trato bem o cliente mesmo num dia difícil. | G13: Comunicação | H13: =IFERROR(AVERAGEIF($B$7:$B$22,G13,$D$7:$D$22),"") | I13: =IFERROR(AVERAGEIF($B$7:$B$22,G13,$E$7:$E$22),"") | J13: =IF(OR(H13="",I13=""),"",I13-H13)
A14: 8 | B14: Atendimento | C14: Resolvo o problema do cliente ou levo a quem resolve. | G14: Aprendizado | H14: =IFERROR(AVERAGEIF($B$7:$B$22,G14,$D$7:$D$22),"") | I14: =IFERROR(AVERAGEIF($B$7:$B$22,G14,$E$7:$E$22),"") | J14: =IF(OR(H14="",I14=""),"",I14-H14)
A15: 9 | B15: Iniciativa | C15: Vejo o que precisa ser feito sem esperar ordem.
A16: 10 | B16: Iniciativa | C16: Sugiro melhorias no meu trabalho. | G16: Diferença positiva: o gestor vê mais do que a pessoa. Negativa: a pessoa se vê melhor. A conversa começa por aí. Cada competência liga a um curso.
A17: 11 | B17: Segurança e normas | C17: Uso os equipamentos de proteção e sigo as regras de segurança.
A18: 12 | B18: Segurança e normas | C18: Mantenho meu posto limpo e organizado.
A19: 13 | B19: Comunicação | C19: Explico com clareza o que preciso ou o que aconteceu.
A20: 14 | B20: Comunicação | C20: Escuto até o fim antes de responder.
A21: 15 | B21: Aprendizado | C21: Aprendo com os erros e não repito.
A22: 16 | B22: Aprendizado | C22: Procuro aprender coisas novas para o trabalho.

Sheet Fontes
A1: Fontes
A2: Só o que ainda é usado: os dois testes. Catálogos de cursos de terceiros e dados regionais ficaram de fora, por decisão do GD em 06/10/2026.
A4: Nº | B4: Fonte | C4: Endereço | D4: O que usei | E4: Como obtive
A5: 1 | B5: IPIP (Big Five), licença | C5: https://ipip.ori.org/ | D5: Itens e escalas em domínio público: uso e tradução livres, inclusive comercial | E5: Página aberta em 06/10/2026
A6: 2 | B6: IPIP: marcadores Big Five | C6: https://ipip.ori.org/newBigFive5broadKey.htm | D6: Lista de itens por fator (as 25 frases da aba Perfil saem daqui) | E6: Página aberta em 06/10/2026
A7: 3 | B7: O*NET Interest Profiler (RIASEC) | C7: https://www.onetcenter.org/IP.html | D7: Licença Creative Commons 4.0 (crédito ao Departamento do Trabalho dos EUA). Usei só o modelo; as frases são nossas | E7: Página aberta em 06/10/2026
